Workbook
Name Slicer_Category: #N/A
Name Slicer_Order_Status: #N/A
Name Slicer_Region: #N/A

Sheet Raw_Data
A1: Order ID | B1: Order Date | C1: Customer ID | D1: Customer Name | E1: Region | F1: City | G1: Product | H1: Category | I1: Quantity | J1: Unit Price | K1: Discount % | L1: Payment Method | M1: Order Status | N1: Expected Delivery Date | O1: Actual Delivery Date | P1: Gross Sales | Q1: Discount Amount | R1: Net Sales | S1: Delivery Days | T1: Delivery Status | U1: Month | V1: Month Start | W1: Cancelled Sales
A2: ORD-10001 | B2: 46137 | C2: CUST-1048 | D2: Customer 1112 | E2: South | F2: Bengaluru | G2: Jeans | H2: Fashion | I2: 1 | J2: 1799 | K2: 0 | L2: COD | M2: Delivered | N2: 46143 | O2: 46138 | P2: =Orders[[#This Row],[Quantity]]*Orders[[#This Row],[Unit Price]] -> 1799 | Q2: =Orders[[#This Row],[Gross Sales]]*Orders[[#This Row],[Discount %]] -> 0 | R2: =Orders[[#This Row],[Gross Sales]]-Orders[[#This Row],[Discount Amount]] -> 1799 | S2: =IF(Orders[[#This Row],[Actual Delivery Date]]="","",Orders[[#This Row],[Actual Delivery Date]]-Orders[[#This Row],[Order Date]]) -> 1 | T2: =IF(Orders[[#This Row],[Actual Delivery Date]]="","Pending",IF(Orders[[#This Row],[Actual Delivery Date]]<=Orders[[#This Row],[Expected Delivery Date]],"On Time","Late")) -> On Time | U2: =TEXT(Orders[[#This Row],[Order Date]],"mmm") -> Apr | V2: =DATE(YEAR(Orders[[#This Row],[Order Date]]),MONTH(Orders[[#This Row],[Order Date]]),1) -> 46113 | W2: =IF(Orders[[#This Row],[Order Status]]="Cancelled",Orders[[#This Row],[Net Sales]],0) -> 0
A3: ORD-10002 | B3: 46355 | C3: CUST-1082 | D3: Customer 1217 | E3: West | F3: Mumbai | G3: Resistance Bands | H3: Sports | I3: 2 | J3: 599 | K3: 0.15 | L3: Credit Card | M3: Delivered | N3: 46361 | O3: 46356 | P3: =Orders[[#This Row],[Quantity]]*Orders[[#This Row],[Unit Price]] -> 1198 | Q3: =Orders[[#This Row],[Gross Sales]]*Orders[[#This Row],[Discount %]] -> 179.7 | R3: =Orders[[#This Row],[Gross Sales]]-Orders[[#This Row],[Discount Amount]] -> 1018.3 | S3: =IF(Orders[[#This Row],[Actual Delivery Date]]="","",Orders[[#This Row],[Actual Delivery Date]]-Orders[[#This Row],[Order Date]]) -> 1 | T3: =IF(Orders[[#This Row],[Actual Delivery Date]]="","Pending",IF(Orders[[#This Row],[Actual Delivery Date]]<=Orders[[#This Row],[Expected Delivery Date]],"On Time","Late")) -> On Time | U3: =TEXT(Orders[[#This Row],[Order Date]],"mmm") -> Nov | V3: =DATE(YEAR(Orders[[#This Row],[Order Date]]),MONTH(Orders[[#This Row],[Order Date]]),1) -> 46327 | W3: =IF(Orders[[#This Row],[Order Status]]="Cancelled",Orders[[#This Row],[Net Sales]],0) -> 0
A4: ORD-10003 | B4: 46195 | C4: CUST-1236 | D4: Customer 1275 | E4: North | F4: Lucknow | G4: Water Bottle | H4: Home | I4: 1 | J4: 699 | K4: 0.15 | L4: UPI | M4: Delivered | N4: 46199 | O4: 46196 | P4: =Orders[[#This Row],[Quantity]]*Orders[[#This Row],[Unit Price]] -> 699 | Q4: =Orders[[#This Row],[Gross Sales]]*Orders[[#This Row],[Discount %]] -> 104.85 | R4: =Orders[[#This Row],[Gross Sales]]-Orders[[#This Row],[Discount Amount]] -> 594.15 | S4: =IF(Orders[[#This Row],[Actual Delivery Date]]="","",Orders[[#This Row],[Actual Delivery Date]]-Orders[[#This Row],[Order Date]]) -> 1 | T4: =IF(Orders[[#This Row],[Actual Delivery Date]]="","Pending",IF(Orders[[#This Row],[Actual Delivery Date]]<=Orders[[#This Row],[Expected Delivery Date]],"On Time","Late")) -> On Time | U4: =TEXT(Orders[[#This Row],[Order Date]],"mmm") -> Jun | V4: =DATE(YEAR(Orders[[#This Row],[Order Date]]),MONTH(Orders[[#This Row],[Order Date]]),1) -> 46174 | W4: =IF(Orders[[#This Row],[Order Status]]="Cancelled",Orders[[#This Row],[Net Sales]],0) -> 0
A5: ORD-10004 | B5: 46173 | C5: CUST-1036 | D5: Customer 1024 | E5: South | F5: Kochi | G5: USB-C Hub | H5: Electronics | I5: 3 | J5: 1799 | K5: 0.2 | L5: Debit Card | M5: Pending | N5: 46176 | P5: =Orders[[#This Row],[Quantity]]*Orders[[#This Row],[Unit Price]] -> 5397 | Q5: =Orders[[#This Row],[Gross Sales]]*Orders[[#This Row],[Discount %]] -> 1079.4 | R5: =Orders[[#This Row],[Gross Sales]]-Orders[[#This Row],[Discount Amount]] -> 4317.6 | S5: =IF(Orders[[#This Row],[Actual Delivery Date]]="","",Orders[[#This Row],[Actual Delivery Date]]-Orders[[#This Row],[Order Date]]) | T5: =IF(Orders[[#This Row],[Actual Delivery Date]]="","Pending",IF(Orders[[#This Row],[Actual Delivery Date]]<=Orders[[#This Row],[Expected Delivery Date]],"On Time","Late")) -> Pending | U5: =TEXT(Orders[[#This Row],[Order Date]],"mmm") -> May | V5: =DATE(YEAR(Orders[[#This Row],[Order Date]]),MONTH(Orders[[#This Row],[Order Date]]),1) -> 46143 | W5: =IF(Orders[[#This Row],[Order Status]]="Cancelled",Orders[[#This Row],[Net Sales]],0) -> 0
A6: ORD-10005 | B6: 46074 | C6: CUST-1037 | D6: Customer 1088 | E6: West | F6: Ahmedabad | G6: Keyboard | H6: Electronics | I6: 1 | J6: 1299 | K6: 0.15 | L6: Debit Card | M6: Delivered | N6: 46078 | O6: 46077 | P6: =Orders[[#This Row],[Quantity]]*Orders[[#This Row],[Unit Price]] -> 1299 | Q6: =Orders[[#This Row],[Gross Sales]]*Orders[[#This Row],[Discount %]] -> 194.85 | R6: =Orders[[#This Row],[Gross Sales]]-Orders[[#This Row],[Discount Amount]] -> 1104.15 | S6: =IF(Orders[[#This Row],[Actual Delivery Date]]="","",Orders[[#This Row],[Actual Delivery Date]]-Orders[[#This Row],[Order Date]]) -> 3 | T6: =IF(Orders[[#This Row],[Actual Delivery Date]]="","Pending",IF(Orders[[#This Row],[Actual Delivery Date]]<=Orders[[#This Row],[Expected Delivery Date]],"On Time","Late")) -> On Time | U6: =TEXT(Orders[[#This Row],[Order Date]],"mmm") -> Feb | V6: =DATE(YEAR(Orders[[#This Row],[Order Date]]),MONTH(Orders[[#This Row],[Order Date]]),1) -> 46054 | W6: =IF(Orders[[#This Row],[Order Status]]="Cancelled",Orders[[#This Row],[Net Sales]],0) -> 0
A7: ORD-10006 | B7: 46161 | C7: CUST-1118 | D7: Customer 1017 | E7: West | F7: Pune | G7: Shampoo | H7: Beauty | I7: 5 | J7: 499 | K7: 0.2 | L7: Credit Card | M7: Cancelled | N7: 46165 | O7: 46162 | P7: =Orders[[#This Row],[Quantity]]*Orders[[#This Row],[Unit Price]] -> 2495 | Q7: =Orders[[#This Row],[Gross Sales]]*Orders[[#This Row],[Discount %]] -> 499 | R7: =Orders[[#This Row],[Gross Sales]]-Orders[[#This Row],[Discount Amount]] -> 1996 | S7: =IF(Orders[[#This Row],[Actual Delivery Date]]="","",Orders[[#This Row],[Actual Delivery Date]]-Orders[[#This Row],[Order Date]]) -> 1 | T7: =IF(Orders[[#This Row],[Actual Delivery Date]]="","Pending",IF(Orders[[#This Row],[Actual Delivery Date]]<=Orders[[#This Row],[Expected Delivery Date]],"On Time","Late")) -> On Time | U7: =TEXT(Orders[[#This Row],[Order Date]],"mmm") -> May | V7: =DATE(YEAR(Orders[[#This Row],[Order Date]]),MONTH(Orders[[#This Row],[Order Date]]),1) -> 46143 | W7: =IF(Orders[[#This Row],[Order Status]]="Cancelled",Orders[[#This Row],[Net Sales]],0) -> 1996
A8: ORD-10007 | B8: 46131 | C8: CUST-1235 | D8: Customer 1074 | E8: North | F8: Chandigarh | G8: T-Shirt | H8: Fashion | I8: 4 | J8: 699 | K8: 0.2 | L8: Debit Card | M8: Delivered | N8: 46138 | O8: 46137 | P8: =Orders[[#This Row],[Quantity]]*Orders[[#This Row],[Unit Price]] -> 2796 | Q8: =Orders[[#This Row],[Gross Sales]]*Orders[[#This Row],[Discount %]] -> 559.2 | R8: =Orders[[#This Row],[Gross Sales]]-Orders[[#This Row],[Discount Amount]] -> 2236.8 | S8: =IF(Orders[[#This Row],[Actual Delivery Date]]="","",Orders[[#This Row],[Actual Delivery Date]]-Orders[[#This Row],[Order Date]]) -> 6 | T8: =IF(Orders[[#This Row],[Actual Delivery Date]]="","Pending",IF(Orders[[#This Row],[Actual Delivery Date]]<=Orders[[#This Row],[Expected Delivery Date]],"On Time","Late")) -> On Time | U8: =TEXT(Orders[[#This Row],[Order Date]],"mmm") -> Apr | V8: =DATE(YEAR(Orders[[#This Row],[Order Date]]),MONTH(Orders[[#This Row],[Order Date]]),1) -> 46113 | W8: =IF(Orders[[#This Row],[Order Status]]="Cancelled",Orders[[#This Row],[Net Sales]],0) -> 0
A9: ORD-10008 | B9: 46298 | C9: CUST-1186 | D9: Customer 1113 | E9: North | F9: Jaipur | G9: Coffee Maker | H9: Home | I9: 1 | J9: 3499 | K9: 0.2 | L9: Net Banking | M9: Pending | N9: 46303 | P9: =Orders[[#This Row],[Quantity]]*Orders[[#This Row],[Unit Price]] -> 3499 | Q9: =Orders[[#This Row],[Gross Sales]]*Orders[[#This Row],[Discount %]] -> 699.8 | R9: =Orders[[#This Row],[Gross Sales]]-Orders[[#This Row],[Discount Amount]] -> 2799.2 | S9: =IF(Orders[[#This Row],[Actual Delivery Date]]="","",Orders[[#This Row],[Actual Delivery Date]]-Orders[[#This Row],[Order Date]]) | T9: =IF(Orders[[#This Row],[Actual Delivery Date]]="","Pending",IF(Orders[[#This Row],[Actual Delivery Date]]<=Orders[[#This Row],[Expected Delivery Date]],"On Time","Late")) -> Pending | U9: =TEXT(Orders[[#This Row],[Order Date]],"mmm") -> Oct | V9: =DATE(YEAR(Orders[[#This Row],[Order Date]]),MONTH(Orders[[#This Row],[Order Date]]),1) -> 46296 | W9: =IF(Orders[[#This Row],[Order Status]]="Cancelled",Orders[[#This Row],[Net Sales]],0) -> 0
A10: ORD-10009 | B10: 46079 | C10: CUST-1198 | D10: Customer 1196 | E10: West | F10: Goa | G10: Wireless Mouse | H10: Electronics | I10: 1 | J10: 799 | K10: 0.05 | L10: Net Banking | M10: Pending | N10: 46081 | P10: =Orders[[#This Row],[Quantity]]*Orders[[#This Row],[Unit Price]] -> 799 | Q10: =Orders[[#This Row],[Gross Sales]]*Orders[[#This Row],[Discount %]] -> 39.95 | R10: =Orders[[#This Row],[Gross Sales]]-Orders[[#This Row],[Discount Amount]] -> 759.05 | S10: =IF(Orders[[#This Row],[Actual Delivery Date]]="","",Orders[[#This Row],[Actual Delivery Date]]-Orders[[#This Row],[Order Date]]) | T10: =IF(Orders[[#This Row],[Actual Delivery Date]]="","Pending",IF(Orders[[#This Row],[Actual Delivery Date]]<=Orders[[#This Row],[Expected Delivery Date]],"On Time","Late")) -> Pending | U10: =TEXT(Orders[[#This Row],[Order Date]],"mmm") -> Feb | V10: =DATE(YEAR(Orders[[#This Row],[Order Date]]),MONTH(Orders[[#This Row],[Order Date]]),1) -> 46054 | W10: =IF(Orders[[#This Row],[Order Status]]="Cancelled",Orders[[#This Row],[Net Sales]],0) -> 0
A11: ORD-10010 | B11: 46371 | C11: CUST-1223 | D11: Customer 1081 | E11: East | F11: Patna | G11: Yoga Mat | H11: Sports | I11: 2 | J11: 899 | K11: 0.2 | L11: Debit Card | M11: Returned | N11: 46378 | O11: 46374 | P11: =Orders[[#This Row],[Quantity]]*Orders[[#This Row],[Unit Price]] -> 1798 | Q11: =Orders[[#This Row],[Gross Sales]]*Orders[[#This Row],[Discount %]] -> 359.6 | R11: =Orders[[#This Row],[Gross Sales]]-Orders[[#This Row],[Discount Amount]] -> 1438.4 | S11: =IF(Orders[[#This Row],[Actual Delivery Date]]="","",Orders[[#This Row],[Actual Delivery Date]]-Orders[[#This Row],[Order Date]]) -> 3 | T11: =IF(Orders[[#This Row],[Actual Delivery Date]]="","Pending",IF(Orders[[#This Row],[Actual Delivery Date]]<=Orders[[#This Row],[Expected Delivery Date]],"On Time","Late")) -> On Time | U11: =TEXT(Orders[[#This Row],[Order Date]],"mmm") -> Dec | V11: =DATE(YEAR(Orders[[#This Row],[Order Date]]),MONTH(Orders[[#This Row],[Order Date]]),1) -> 46357 | W11: =IF(Orders[[#This Row],[Order Status]]="Cancelled",Orders[[#This Row],[Net Sales]],0) -> 0
A12: ORD-10011 | B12: 46114 | C12: CUST-1079 | D12: Customer 1192 | E12: East | F12: Kolkata | G12: Backpack | H12: Fashion | I12: 2 | J12: 1899 | K12: 0 | L12: Debit Card | M12: Returned | N12: 46121 | O12: 46116 | P12: =Orders[[#This Row],[Quantity]]*Orders[[#This Row],[Unit Price]] -> 3798 | Q12: =Orders[[#This Row],[Gross Sales]]*Orders[[#This Row],[Discount %]] -> 0 | R12: =Orders[[#This Row],[Gross Sales]]-Orders[[#This Row],[Discount Amount]] -> 3798 | S12: =IF(Orders[[#This Row],[Actual Delivery Date]]="","",Orders[[#This Row],[Actual Delivery Date]]-Orders[[#This Row],[Order Date]]) -> 2 | T12: =IF(Orders[[#This Row],[Actual Delivery Date]]="","Pending",IF(Orders[[#This Row],[Actual Delivery Date]]<=Orders[[#This Row],[Expected Delivery Date]],"On Time","Late")) -> On Time | U12: =TEXT(Orders[[#This Row],[Order Date]],"mmm") -> Apr | V12: =DATE(YEAR(Orders[[#This Row],[Order Date]]),MONTH(Orders[[#This Row],[Order Date]]),1) -> 46113 | W12: =IF(Orders[[#This Row],[Order Status]]="Cancelled",Orders[[#This Row],[Net Sales]],0) -> 0
A13: ORD-10012 | B13: 46273 | C13: CUST-1044 | D13: Customer 1249 | E13: West | F13: Mumbai | G13: Running Shoes | H13: Sports | I13: 1 | J13: 3299 | K13: 0.1 | L13: Debit Card | M13: Delivered | N13: 46275 | O13: 46274 | P13: =Orders[[#This Row],[Quantity]]*Orders[[#This Row],[Unit Price]] -> 3299 | Q13: =Orders[[#This Row],[Gross Sales]]*Orders[[#This Row],[Discount %]] -> 329.9 | R13: =Orders[[#This Row],[Gross Sales]]-Orders[[#This Row],[Discount Amount]] -> 2969.1 | S13: =IF(Orders[[#This Row],[Actual Delivery Date]]="","",Orders[[#This Row],[Actual Delivery Date]]-Orders[[#This Row],[Order Date]]) -> 1 | T13: =IF(Orders[[#This Row],[Actual Delivery Date]]="","Pending",IF(Orders[[#This Row],[Actual Delivery Date]]<=Orders[[#This Row],[Expected Delivery Date]],"On Time","Late")) -> On Time | U13: =TEXT(Orders[[#This Row],[Order Date]],"mmm") -> Sep | V13: =DATE(YEAR(Orders[[#This Row],[Order Date]]),MONTH(Orders[[#This Row],[Order Date]]),1) -> 46266 | W13: =IF(Orders[[#This Row],[Order Status]]="Cancelled",Orders[[#This Row],[Net Sales]],0) -> 0
A14: ORD-10013 | B14: 46304 | C14: CUST-1160 | D14: Customer 1205 | E14: South | F14: Chennai | G14: Bedsheet Set | H14: Home | I14: 1 | J14: 1599 | K14: 0.2 | L14: COD | M14: Delivered | N14: 46307 | O14: 46309 | P14: =Orders[[#This Row],[Quantity]]*Orders[[#This Row],[Unit Price]] -> 1599 | Q14: =Orders[[#This Row],[Gross Sales]]*Orders[[#This Row],[Discount %]] -> 319.8 | R14: =Orders[[#This Row],[Gross Sales]]-Orders[[#This Row],[Discount Amount]] -> 1279.2 | S14: =IF(Orders[[#This Row],[Actual Delivery Date]]="","",Orders[[#This Row],[Actual Delivery Date]]-Orders[[#This Row],[Order Date]]) -> 5 | T14: =IF(Orders[[#This Row],[Actual Delivery Date]]="","Pending",IF(Orders[[#This Row],[Actual Delivery Date]]<=Orders[[#This Row],[Expected Delivery Date]],"On Time","Late")) -> Late | U14: =TEXT(Orders[[#This Row],[Order Date]],"mmm") -> Oct | V14: =DATE(YEAR(Orders[[#This Row],[Order Date]]),MONTH(Orders[[#This Row],[Order Date]]),1) -> 46296 | W14: =IF(Orders[[#This Row],[Order Status]]="Cancelled",Orders[[#This Row],[Net Sales]],0) -> 0
A15: ORD-10014 | B15: 46084 | C15: CUST-1113 | D15: Customer 1004 | E15: North | F15: Chandigarh | G15: Cricket Bat | H15: Sports | I15: 1 | J15: 2499 | K15: 0 | L15: Debit Card | M15: Delivered | N15: 46090 | O15: 46089 | P15: =Orders[[#This Row],[Quantity]]*Orders[[#This Row],[Unit Price]] -> 2499 | Q15: =Orders[[#This Row],[Gross Sales]]*Orders[[#This Row],[Discount %]] -> 0 | R15: =Orders[[#This Row],[Gross Sales]]-Orders[[#This Row],[Discount Amount]] -> 2499 | S15: =IF(Orders[[#This Row],[Actual Delivery Date]]="","",Orders[[#This Row],[Actual Delivery Date]]-Orders[[#This Row],[Order Date]]) -> 5 | T15: =IF(Orders[[#This Row],[Actual Delivery Date]]="","Pending",IF(Orders[[#This Row],[Actual Delivery Date]]<=Orders[[#This Row],[Expected Delivery Date]],"On Time","Late")) -> On Time | U15: =TEXT(Orders[[#This Row],[Order Date]],"mmm") -> Mar | V15: =DATE(YEAR(Orders[[#This Row],[Order Date]]),MONTH(Orders[[#This Row],[Order Date]]),1) -> 46082 | W15: =IF(Orders[[#This Row],[Order Status]]="Cancelled",Orders[[#This Row],[Net Sales]],0) -> 0
A16: ORD-10015 | B16: 46039 | C16: CUST-1277 | D16: Customer 1068 | E16: South | F16: Bengaluru | G16: Desk Lamp | H16: Home | I16: 3 | J16: 999 | K16: 0 | L16: COD | M16: Delivered | N16: 46043 | O16: 46041 | P16: =Orders[[#This Row],[Quantity]]*Orders[[#This Row],[Unit Price]] -> 2997 | Q16: =Orders[[#This Row],[Gross Sales]]*Orders[[#This Row],[Discount %]] -> 0 | R16: =Orders[[#This Row],[Gross Sales]]-Orders[[#This Row],[Discount Amount]] -> 2997 | S16: =IF(Orders[[#This Row],[Actual Delivery Date]]="","",Orders[[#This Row],[Actual Delivery Date]]-Orders[[#This Row],[Order Date]]) -> 2 | T16: =IF(Orders[[#This Row],[Actual Delivery Date]]="","Pending",IF(Orders[[#This Row],[Actual Delivery Date]]<=Orders[[#This Row],[Expected Delivery Date]],"On Time","Late")) -> On Time | U16: =TEXT(Orders[[#This Row],[Order Date]],"mmm") -> Jan | V16: =DATE(YEAR(Orders[[#This Row],[Order Date]]),MONTH(Orders[[#This Row],[Order Date]]),1) -> 46023 | W16: =IF(Orders[[#This Row],[Order Status]]="Cancelled",Orders[[#This Row],[Net Sales]],0) -> 0
A17: ORD-10016 | B17: 46120 | C17: CUST-1051 | D17: Customer 1032 | E17: East | F17: Bhubaneswar | G17: Shampoo | H17: Beauty | I17: 1 | J17: 499 | K17: 0.15 | L17: Debit Card | M17: Delivered | N17: 46125 | O17: 46121 | P17: =Orders[[#This Row],[Quantity]]*Orders[[#This Row],[Unit Price]] -> 499 | Q17: =Orders[[#This Row],[Gross Sales]]*Orders[[#This Row],[Discount %]] -> 74.85 | R17: =Orders[[#This Row],[Gross Sales]]-Orders[[#This Row],[Discount Amount]] -> 424.15 | S17: =IF(Orders[[#This Row],[Actual Delivery Date]]="","",Orders[[#This Row],[Actual Delivery Date]]-Orders[[#This Row],[Order Date]]) -> 1 | T17: =IF(Orders[[#This Row],[Actual Delivery Date]]="","Pending",IF(Orders[[#This Row],[Actual Delivery Date]]<=Orders[[#This Row],[Expected Delivery Date]],"On Time","Late")) -> On Time | U17: =TEXT(Orders[[#This Row],[Order Date]],"mmm") -> Apr | V17: =DATE(YEAR(Orders[[#This Row],[Order Date]]),MONTH(Orders[[#This Row],[Order Date]]),1) -> 46113 | W17: =IF(Orders[[#This Row],[Order Status]]="Cancelled",Orders[[#This Row],[Net Sales]],0) -> 0
A18: ORD-10017 | B18: 46121 | C18: CUST-1039 | D18: Customer 1227 | E18: East | F18: Patna | G18: Keyboard | H18: Electronics | I18: 1 | J18: 1299 | K18: 0.15 | L18: Credit Card | M18: Delivered | N18: 46124 | O18: 46122 | P18: =Orders[[#This Row],[Quantity]]*Orders[[#This Row],[Unit Price]] -> 1299 | Q18: =Orders[[#This Row],[Gross Sales]]*Orders[[#This Row],[Discount %]] -> 194.85 | R18: =Orders[[#This Row],[Gross Sales]]-Orders[[#This Row],[Discount Amount]] -> 1104.15 | S18: =IF(Orders[[#This Row],[Actual Delivery Date]]="","",Orders[[#This Row],[Actual Delivery Date]]-Orders[[#This Row],[Order Date]]) -> 1 | T18: =IF(Orders[[#This Row],[Actual Delivery Date]]="","Pending",IF(Orders[[#This Row],[Actual Delivery Date]]<=Orders[[#This Row],[Expected Delivery Date]],"On Time","Late")) -> On Time | U18: =TEXT(Orders[[#This Row],[Order Date]],"mmm") -> Apr | V18: =DATE(YEAR(Orders[[#This Row],[Order Date]]),MONTH(Orders[[#This Row],[Order Date]]),1) -> 46113 | W18: =IF(Orders[[#This Row],[Order Status]]="Cancelled",Orders[[#This Row],[Net Sales]],0) -> 0
A19: ORD-10018 | B19: 46070 | C19: CUST-1031 | D19: Customer 1085 | E19: South | F19: Bengaluru | G19: Yoga Mat | H19: Sports | I19: 4 | J19: 899 | K19: 0.05 | L19: Credit Card | M19: Delivered | N19: 46075 | O19: 46074 | P19: =Orders[[#This Row],[Quantity]]*Orders[[#This Row],[Unit Price]] -> 3596 | Q19: =Orders[[#This Row],[Gross Sales]]*Orders[[#This Row],[Discount %]] -> 179.8 | R19: =Orders[[#This Row],[Gross Sales]]-Orders[[#This Row],[Discount Amount]] -> 3416.2 | S19: =IF(Orders[[#This Row],[Actual Delivery Date]]="","",Orders[[#This Row],[Actual Delivery Date]]-Orders[[#This Row],[Order Date]]) -> 4 | T19: =IF(Orders[[#This Row],[Actual Delivery Date]]="","Pending",IF(Orders[[#This Row],[Actual Delivery Date]]<=Orders[[#This Row],[Expected Delivery Date]],"On Time","Late")) -> On Time | U19: =TEXT(Orders[[#This Row],[Order Date]],"mmm") -> Feb | V19: =DATE(YEAR(Orders[[#This Row],[Order Date]]),MONTH(Orders[[#This Row],[Order Date]]),1) -> 46054 | W19: =IF(Orders[[#This Row],[Order Status]]="Cancelled",Orders[[#This Row],[Net Sales]],0) -> 0
A20: ORD-10019 | B20: 46255 | C20: CUST-1297 | D20: Customer 1278 | E20: East | F20: Kolkata | G20: Sunscreen | H20: Beauty | I20: 1 | J20: 749 | K20: 0.2 | L20: Net Banking | M20: Delivered | N20: 46258 | O20: 46256 | P20: =Orders[[#This Row],[Quantity]]*Orders[[#This Row],[Unit Price]] -> 749 | Q20: =Orders[[#This Row],[Gross Sales]]*Orders[[#This Row],[Discount %]] -> 149.8 | R20: =Orders[[#This Row],[Gross Sales]]-Orders[[#This Row],[Discount Amount]] -> 599.2 | S20: =IF(Orders[[#This Row],[Actual Delivery Date]]="","",Orders[[#This Row],[Actual Delivery Date]]-Orders[[#This Row],[Order Date]]) -> 1 | T20: =IF(Orders[[#This Row],[Actual Delivery Date]]="","Pending",IF(Orders[[#This Row],[Actual Delivery Date]]<=Orders[[#This Row],[Expected Delivery Date]],"On Time","Late")) -> On Time | U20: =TEXT(Orders[[#This Row],[Order Date]],"mmm") -> Aug | V20: =DATE(YEAR(Orders[[#This Row],[Order Date]]),MONTH(Orders[[#This Row],[Order Date]]),1) -> 46235 | W20: =IF(Orders[[#This Row],[Order Status]]="Cancelled",Orders[[#This Row],[Net Sales]],0) -> 0
A21: ORD-10020 | B21: 46322 | C21: CUST-1036 | D21: Customer 1035 | E21: South | F21: Hyderabad | G21: Wireless Mouse | H21: Electronics | I21: 2 | J21: 799 | K21: 0.2 | L21: Credit Card | M21: Delivered | N21: 46328 | O21: 46324 | P21: =Orders[[#This Row],[Quantity]]*Orders[[#This Row],[Unit Price]] -> 1598 | Q21: =Orders[[#This Row],[Gross Sales]]*Orders[[#This Row],[Discount %]] -> 319.6 | R21: =Orders[[#This Row],[Gross Sales]]-Orders[[#This Row],[Discount Amount]] -> 1278.4 | S21: =IF(Orders[[#This Row],[Actual Delivery Date]]="","",Orders[[#This Row],[Actual Delivery Date]]-Orders[[#This Row],[Order Date]]) -> 2 | T21: =IF(Orders[[#This Row],[Actual Delivery Date]]="","Pending",IF(Orders[[#This Row],[Actual Delivery Date]]<=Orders[[#This Row],[Expected Delivery Date]],"On Time","Late")) -> On Time | U21: =TEXT(Orders[[#This Row],[Order Date]],"mmm") -> Oct | V21: =DATE(YEAR(Orders[[#This Row],[Order Date]]),MONTH(Orders[[#This Row],[Order Date]]),1) -> 46296 | W21: =IF(Orders[[#This Row],[Order Status]]="Cancelled",Orders[[#This Row],[Net Sales]],0) -> 0
A22: ORD-10021 | B22: 46149 | C22: CUST-1268 | D22: Customer 1162 | E22: West | F22: Goa | G22: USB-C Hub | H22: Electronics | I22: 2 | J22: 1799 | K22: 0 | L22: COD | M22: Delivered | N22: 46154 | O22: 46154 | P22: =Orders[[#This Row],[Quantity]]*Orders[[#This Row],[Unit Price]] -> 3598 | Q22: =Orders[[#This Row],[Gross Sales]]*Orders[[#This Row],[Discount %]] -> 0 | R22: =Orders[[#This Row],[Gross Sales]]-Orders[[#This Row],[Discount Amount]] -> 3598 | S22: =IF(Orders[[#This Row],[Actual Delivery Date]]="","",Orders[[#This Row],[Actual Delivery Date]]-Orders[[#This Row],[Order Date]]) -> 5 | T22: =IF(Orders[[#This Row],[Actual Delivery Date]]="","Pending",IF(Orders[[#This Row],[Actual Delivery Date]]<=Orders[[#This Row],[Expected Delivery Date]],"On Time","Late")) -> On Time | U22: =TEXT(Orders[[#This Row],[Order Date]],"mmm") -> May | V22: =DATE(YEAR(Orders[[#This Row],[Order Date]]),MONTH(Orders[[#This Row],[Order Date]]),1) -> 46143 | W22: =IF(Orders[[#This Row],[Order Status]]="Cancelled",Orders[[#This Row],[Net Sales]],0) -> 0
... A31: ORD-10030 | B31: 46202 | C31: CUST-1092 | D31: Customer 1298 | E31: North | F31: Lucknow | G31: Bluetooth Speaker | H31: Electronics | I31: 2 | J31: 1999 | K31: 0.15 | L31: COD | M31: Delivered | N31: 46204 | O31: 46204 | P31: =Orders[[#This Row],[Quantity]]*Orders[[#This Row],[Unit Price]] -> 3998 | Q31: =Orders[[#This Row],[Gross Sales]]*Orders[[#This Row],[Discount %]] -> 599.7 | R31: =Orders[[#This Row],[Gross Sales]]-Orders[[#This Row],[Discount Amount]] -> 3398.3 | S31: =IF(Orders[[#This Row],[Actual Delivery Date]]="","",Orders[[#This Row],[Actual Delivery Date]]-Orders[[#This Row],[Order Date]]) -> 2 | T31: =IF(Orders[[#This Row],[Actual Delivery Date]]="","Pending",IF(Orders[[#This Row],[Actual Delivery Date]]<=Orders[[#This Row],[Expected Delivery Date]],"On Time","Late")) -> On Time | U31: =TEXT(Orders[[#This Row],[Order Date]],"mmm") -> Jun | V31: =DATE(YEAR(Orders[[#This Row],[Order Date]]),MONTH(Orders[[#This Row],[Order Date]]),1) -> 46174 | W31: =IF(Orders[[#This Row],[Order Status]]="Cancelled",Orders[[#This Row],[Net Sales]],0) -> 0
A32: ORD-10031 | B32: 46245 | C32: CUST-1060 | D32: Customer 1198 | E32: North | F32: Delhi | G32: USB-C Hub | H32: Electronics | I32: 1 | J32: 1799 | K32: 0.1 | L32: Net Banking | M32: Pending | N32: 46251 | P32: =Orders[[#This Row],[Quantity]]*Orders[[#This Row],[Unit Price]] -> 1799 | Q32: =Orders[[#This Row],[Gross Sales]]*Orders[[#This Row],[Discount %]] -> 179.9 | R32: =Orders[[#This Row],[Gross Sales]]-Orders[[#This Row],[Discount Amount]] -> 1619.1 | S32: =IF(Orders[[#This Row],[Actual Delivery Date]]="","",Orders[[#This Row],[Actual Delivery Date]]-Orders[[#This Row],[Order Date]]) | T32: =IF(Orders[[#This Row],[Actual Delivery Date]]="","Pending",IF(Orders[[#This Row],[Actual Delivery Date]]<=Orders[[#This Row],[Expected Delivery Date]],"On Time","Late")) -> Pending | U32: =TEXT(Orders[[#This Row],[Order Date]],"mmm") -> Aug | V32: =DATE(YEAR(Orders[[#This Row],[Order Date]]),MONTH(Orders[[#This Row],[Order Date]]),1) -> 46235 | W32: =IF(Orders[[#This Row],[Order Status]]="Cancelled",Orders[[#This Row],[Net Sales]],0) -> 0
A33: ORD-10032 | B33: 46023 | C33: CUST-1161 | D33: Customer 1064 | E33: West | F33: Ahmedabad | G33: Power Bank | H33: Electronics | I33: 2 | J33: 1499 | K33: 0.2 | L33: Credit Card | M33: Delivered | N33: 46028 | O33: 46026 | P33: =Orders[[#This Row],[Quantity]]*Orders[[#This Row],[Unit Price]] -> 2998 | Q33: =Orders[[#This Row],[Gross Sales]]*Orders[[#This Row],[Discount %]] -> 599.6 | R33: =Orders[[#This Row],[Gross Sales]]-Orders[[#This Row],[Discount Amount]] -> 2398.4 | S33: =IF(Orders[[#This Row],[Actual Delivery Date]]="","",Orders[[#This Row],[Actual Delivery Date]]-Orders[[#This Row],[Order Date]]) -> 3 | T33: =IF(Orders[[#This Row],[Actual Delivery Date]]="","Pending",IF(Orders[[#This Row],[Actual Delivery Date]]<=Orders[[#This Row],[Expected Delivery Date]],"On Time","Late")) -> On Time | U33: =TEXT(Orders[[#This Row],[Order Date]],"mmm") -> Jan | V33: =DATE(YEAR(Orders[[#This Row],[Order Date]]),MONTH(Orders[[#This Row],[Order Date]]),1) -> 46023 | W33: =IF(Orders[[#This Row],[Order Status]]="Cancelled",Orders[[#This Row],[Net Sales]],0) -> 0
A34: ORD-10033 | B34: 46229 | C34: CUST-1090 | D34: Customer 1292 | E34: North | F34: Lucknow | G34: Sunscreen | H34: Beauty | I34: 2 | J34: 749 | K34: 0.2 | L34: Credit Card | M34: Delivered | N34: 46234 | O34: 46233 | P34: =Orders[[#This Row],[Quantity]]*Orders[[#This Row],[Unit Price]] -> 1498 | Q34: =Orders[[#This Row],[Gross Sales]]*Orders[[#This Row],[Discount %]] -> 299.6 | R34: =Orders[[#This Row],[Gross Sales]]-Orders[[#This Row],[Discount Amount]] -> 1198.4 | S34: =IF(Orders[[#This Row],[Actual Delivery Date]]="","",Orders[[#This Row],[Actual Delivery Date]]-Orders[[#This Row],[Order Date]]) -> 4 | T34: =IF(Orders[[#This Row],[Actual Delivery Date]]="","Pending",IF(Orders[[#This Row],[Actual Delivery Date]]<=Orders[[#This Row],[Expected Delivery Date]],"On Time","Late")) -> On Time | U34: =TEXT(Orders[[#This Row],[Order Date]],"mmm") -> Jul | V34: =DATE(YEAR(Orders[[#This Row],[Order Date]]),MONTH(Orders[[#This Row],[Order Date]]),1) -> 46204 | W34: =IF(Orders[[#This Row],[Order Status]]="Cancelled",Orders[[#This Row],[Net Sales]],0) -> 0
A35: ORD-10034 | B35: 46178 | C35: CUST-1165 | D35: Customer 1239 | E35: North | F35: Chandigarh | G35: Yoga Mat | H35: Sports | I35: 1 | J35: 899 | K35: 0.15 | L35: COD | M35: Pending | N35: 46185 | P35: =Orders[[#This Row],[Quantity]]*Orders[[#This Row],[Unit Price]] -> 899 | Q35: =Orders[[#This Row],[Gross Sales]]*Orders[[#This Row],[Discount %]] -> 134.85 | R35: =Orders[[#This Row],[Gross Sales]]-Orders[[#This Row],[Discount Amount]] -> 764.15 | S35: =IF(Orders[[#This Row],[Actual Delivery Date]]="","",Orders[[#This Row],[Actual Delivery Date]]-Orders[[#This Row],[Order Date]]) | T35: =IF(Orders[[#This Row],[Actual Delivery Date]]="","Pending",IF(Orders[[#This Row],[Actual Delivery Date]]<=Orders[[#This Row],[Expected Delivery Date]],"On Time","Late")) -> Pending | U35: =TEXT(Orders[[#This Row],[Order Date]],"mmm") -> Jun | V35: =DATE(YEAR(Orders[[#This Row],[Order Date]]),MONTH(Orders[[#This Row],[Order Date]]),1) -> 46174 | W35: =IF(Orders[[#This Row],[Order Status]]="Cancelled",Orders[[#This Row],[Net Sales]],0) -> 0
A36: ORD-10035 | B36: 46265 | C36: CUST-1172 | D36: Customer 1048 | E36: East | F36: Guwahati | G36: Coffee Maker | H36: Home | I36: 3 | J36: 3499 | K36: 0.05 | L36: UPI | M36: Delivered | N36: 46271 | O36: 46270 | P36: =Orders[[#This Row],[Quantity]]*Orders[[#This Row],[Unit Price]] -> 10497 | Q36: =Orders[[#This Row],[Gross Sales]]*Orders[[#This Row],[Discount %]] -> 524.85 | R36: =Orders[[#This Row],[Gross Sales]]-Orders[[#This Row],[Discount Amount]] -> 9972.15 | S36: =IF(Orders[[#This Row],[Actual Delivery Date]]="","",Orders[[#This Row],[Actual Delivery Date]]-Orders[[#This Row],[Order Date]]) -> 5 | T36: =IF(Orders[[#This Row],[Actual Delivery Date]]="","Pending",IF(Orders[[#This Row],[Actual Delivery Date]]<=Orders[[#This Row],[Expected Delivery Date]],"On Time","Late")) -> On Time | U36: =TEXT(Orders[[#This Row],[Order Date]],"mmm") -> Aug | V36: =DATE(YEAR(Orders[[#This Row],[Order Date]]),MONTH(Orders[[#This Row],[Order Date]]),1) -> 46235 | W36: =IF(Orders[[#This Row],[Order Status]]="Cancelled",Orders[[#This Row],[Net Sales]],0) -> 0
A37: ORD-10036 | B37: 46098 | C37: CUST-1234 | D37: Customer 1213 | E37: West | F37: Ahmedabad | G37: Water Bottle | H37: Home | I37: 1 | J37: 699 | K37: 0.05 | L37: Net Banking | M37: Pending | N37: 46100 | P37: =Orders[[#This Row],[Quantity]]*Orders[[#This Row],[Unit Price]] -> 699 | Q37: =Orders[[#This Row],[Gross Sales]]*Orders[[#This Row],[Discount %]] -> 34.95 | R37: =Orders[[#This Row],[Gross Sales]]-Orders[[#This Row],[Discount Amount]] -> 664.05 | S37: =IF(Orders[[#This Row],[Actual Delivery Date]]="","",Orders[[#This Row],[Actual Delivery Date]]-Orders[[#This Row],[Order Date]]) | T37: =IF(Orders[[#This Row],[Actual Delivery Date]]="","Pending",IF(Orders[[#This Row],[Actual Delivery Date]]<=Orders[[#This Row],[Expected Delivery Date]],"On Time","Late")) -> Pending | U37: =TEXT(Orders[[#This Row],[Order Date]],"mmm") -> Mar | V37: =DATE(YEAR(Orders[[#This Row],[Order Date]]),MONTH(Orders[[#This Row],[Order Date]]),1) -> 46082 | W37: =IF(Orders[[#This Row],[Order Status]]="Cancelled",Orders[[#This Row],[Net Sales]],0) -> 0
A38: ORD-10037 | B38: 46147 | C38: CUST-1238 | D38: Customer 1026 | E38: West | F38: Goa | G38: Shampoo | H38: Beauty | I38: 1 | J38: 499 | K38: 0 | L38: UPI | M38: Returned | N38: 46152 | O38: 46152 | P38: =Orders[[#This Row],[Quantity]]*Orders[[#This Row],[Unit Price]] -> 499 | Q38: =Orders[[#This Row],[Gross Sales]]*Orders[[#This Row],[Discount %]] -> 0 | R38: =Orders[[#This Row],[Gross Sales]]-Orders[[#This Row],[Discount Amount]] -> 499 | S38: =IF(Orders[[#This Row],[Actual Delivery Date]]="","",Orders[[#This Row],[Actual Delivery Date]]-Orders[[#This Row],[Order Date]]) -> 5 | T38: =IF(Orders[[#This Row],[Actual Delivery Date]]="","Pending",IF(Orders[[#This Row],[Actual Delivery Date]]<=Orders[[#This Row],[Expected Delivery Date]],"On Time","Late")) -> On Time | U38: =TEXT(Orders[[#This Row],[Order Date]],"mmm") -> May | V38: =DATE(YEAR(Orders[[#This Row],[Order Date]]),MONTH(Orders[[#This Row],[Order Date]]),1) -> 46143 | W38: =IF(Orders[[#This Row],[Order Status]]="Cancelled",Orders[[#This Row],[Net Sales]],0) -> 0
A39: ORD-10038 | B39: 46260 | C39: CUST-1219 | D39: Customer 1281 | E39: West | F39: Mumbai | G39: Moisturizer | H39: Beauty | I39: 2 | J39: 599 | K39: 0.2 | L39: COD | M39: Delivered | N39: 46265 | O39: 46265 | P39: =Orders[[#This Row],[Quantity]]*Orders[[#This Row],[Unit Price]] -> 1198 | Q39: =Orders[[#This Row],[Gross Sales]]*Orders[[#This Row],[Discount %]] -> 239.6 | R39: =Orders[[#This Row],[Gross Sales]]-Orders[[#This Row],[Discount Amount]] -> 958.4 | S39: =IF(Orders[[#This Row],[Actual Delivery Date]]="","",Orders[[#This Row],[Actual Delivery Date]]-Orders[[#This Row],[Order Date]]) -> 5 | T39: =IF(Orders[[#This Row],[Actual Delivery Date]]="","Pending",IF(Orders[[#This Row],[Actual Delivery Date]]<=Orders[[#This Row],[Expected Delivery Date]],"On Time","Late")) -> On Time | U39: =TEXT(Orders[[#This Row],[Order Date]],"mmm") -> Aug | V39: =DATE(YEAR(Orders[[#This Row],[Order Date]]),MONTH(Orders[[#This Row],[Order Date]]),1) -> 46235 | W39: =IF(Orders[[#This Row],[Order Status]]="Cancelled",Orders[[#This Row],[Net Sales]],0) -> 0
A40: ORD-10039 | B40: 46155 | C40: CUST-1040 | D40: Customer 1147 | E40: East | F40: Bhubaneswar | G40: Shampoo | H40: Beauty | I40: 3 | J40: 499 | K40: 0.1 | L40: COD | M40: Delivered | N40: 46162 | O40: 46159 | P40: =Orders[[#This Row],[Quantity]]*Orders[[#This Row],[Unit Price]] -> 1497 | Q40: =Orders[[#This Row],[Gross Sales]]*Orders[[#This Row],[Discount %]] -> 149.7 | R40: =Orders[[#This Row],[Gross Sales]]-Orders[[#This Row],[Discount Amount]] -> 1347.3 | S40: =IF(Orders[[#This Row],[Actual Delivery Date]]="","",Orders[[#This Row],[Actual Delivery Date]]-Orders[[#This Row],[Order Date]]) -> 4 | T40: =IF(Orders[[#This Row],[Actual Delivery Date]]="","Pending",IF(Orders[[#This Row],[Actual Delivery Date]]<=Orders[[#This Row],[Expected Delivery Date]],"On Time","Late")) -> On Time | U40: =TEXT(Orders[[#This Row],[Order Date]],"mmm") -> May | V40: =DATE(YEAR(Orders[[#This Row],[Order Date]]),MONTH(Orders[[#This Row],[Order Date]]),1) -> 46143 | W40: =IF(Orders[[#This Row],[Order Status]]="Cancelled",Orders[[#This Row],[Net Sales]],0) -> 0
A41: ORD-10040 | B41: 46299 | C41: CUST-1033 | D41: Customer 1213 | E41: West | F41: Ahmedabad | G41: Hoodie | H41: Fashion | I41: 1 | J41: 1999 | K41: 0.05 | L41: Credit Card | M41: Delivered | N41: 46306 | O41: 46301 | P41: =Orders[[#This Row],[Quantity]]*Orders[[#This Row],[Unit Price]] -> 1999 | Q41: =Orders[[#This Row],[Gross Sales]]*Orders[[#This Row],[Discount %]] -> 99.95 | R41: =Orders[[#This Row],[Gross Sales]]-Orders[[#This Row],[Discount Amount]] -> 1899.05 | S41: =IF(Orders[[#This Row],[Actual Delivery Date]]="","",Orders[[#This Row],[Actual Delivery Date]]-Orders[[#This Row],[Order Date]]) -> 2 | T41: =IF(Orders[[#This Row],[Actual Delivery Date]]="","Pending",IF(Orders[[#This Row],[Actual Delivery Date]]<=Orders[[#This Row],[Expected Delivery Date]],"On Time","Late")) -> On Time | U41: =TEXT(Orders[[#This Row],[Order Date]],"mmm") -> Oct | V41: =DATE(YEAR(Orders[[#This Row],[Order Date]]),MONTH(Orders[[#This Row],[Order Date]]),1) -> 46296 | W41: =IF(Orders[[#This Row],[Order Status]]="Cancelled",Orders[[#This Row],[Net Sales]],0) -> 0
A42: ORD-10041 | B42: 46235 | C42: CUST-1295 | D42: Customer 1195 | E42: East | F42: Patna | G42: Cricket Bat | H42: Sports | I42: 1 | J42: 2499 | K42: 0.15 | L42: Net Banking | M42: Returned | N42: 46241 | O42: 46242 | P42: =Orders[[#This Row],[Quantity]]*Orders[[#This Row],[Unit Price]] -> 2499 | Q42: =Orders[[#This Row],[Gross Sales]]*Orders[[#This Row],[Discount %]] -> 374.85 | R42: =Orders[[#This Row],[Gross Sales]]-Orders[[#This Row],[Discount Amount]] -> 2124.15 | S42: =IF(Orders[[#This Row],[Actual Delivery Date]]="","",Orders[[#This Row],[Actual Delivery Date]]-Orders[[#This Row],[Order Date]]) -> 7 | T42: =IF(Orders[[#This Row],[Actual Delivery Date]]="","Pending",IF(Orders[[#This Row],[Actual Delivery Date]]<=Orders[[#This Row],[Expected Delivery Date]],"On Time","Late")) -> Late | U42: =TEXT(Orders[[#This Row],[Order Date]],"mmm") -> Aug | V42: =DATE(YEAR(Orders[[#This Row],[Order Date]]),MONTH(Orders[[#This Row],[Order Date]]),1) -> 46235 | W42: =IF(Orders[[#This Row],[Order Status]]="Cancelled",Orders[[#This Row],[Net Sales]],0) -> 0
A43: ORD-10042 | B43: 46222 | C43: CUST-1113 | D43: Customer 1250 | E43: East | F43: Kolkata | G43: Hoodie | H43: Fashion | I43: 3 | J43: 1999 | K43: 0.15 | L43: COD | M43: Cancelled | N43: 46229 | O43: 46227 | P43: =Orders[[#This Row],[Quantity]]*Orders[[#This Row],[Unit Price]] -> 5997 | Q43: =Orders[[#This Row],[Gross Sales]]*Orders[[#This Row],[Discount %]] -> 899.55 | R43: =Orders[[#This Row],[Gross Sales]]-Orders[[#This Row],[Discount Amount]] -> 5097.45 | S43: =IF(Orders[[#This Row],[Actual Delivery Date]]="","",Orders[[#This Row],[Actual Delivery Date]]-Orders[[#This Row],[Order Date]]) -> 5 | T43: =IF(Orders[[#This Row],[Actual Delivery Date]]="","Pending",IF(Orders[[#This Row],[Actual Delivery Date]]<=Orders[[#This Row],[Expected Delivery Date]],"On Time","Late")) -> On Time | U43: =TEXT(Orders[[#This Row],[Order Date]],"mmm") -> Jul | V43: =DATE(YEAR(Orders[[#This Row],[Order Date]]),MONTH(Orders[[#This Row],[Order Date]]),1) -> 46204 | W43: =IF(Orders[[#This Row],[Order Status]]="Cancelled",Orders[[#This Row],[Net Sales]],0) -> 5097.45
A44: ORD-10043 | B44: 46037 | C44: CUST-1202 | D44: Customer 1289 | E44: West | F44: Ahmedabad | G44: Shampoo | H44: Beauty | I44: 1 | J44: 499 | K44: 0.15 | L44: Credit Card | M44: Returned | N44: 46042 | O44: 46043 | P44: =Orders[[#This Row],[Quantity]]*Orders[[#This Row],[Unit Price]] -> 499 | Q44: =Orders[[#This Row],[Gross Sales]]*Orders[[#This Row],[Discount %]] -> 74.85 | R44: =Orders[[#This Row],[Gross Sales]]-Orders[[#This Row],[Discount Amount]] -> 424.15 | S44: =IF(Orders[[#This Row],[Actual Delivery Date]]="","",Orders[[#This Row],[Actual Delivery Date]]-Orders[[#This Row],[Order Date]]) -> 6 | T44: =IF(Orders[[#This Row],[Actual Delivery Date]]="","Pending",IF(Orders[[#This Row],[Actual Delivery Date]]<=Orders[[#This Row],[Expected Delivery Date]],"On Time","Late")) -> Late | U44: =TEXT(Orders[[#This Row],[Order Date]],"mmm") -> Jan | V44: =DATE(YEAR(Orders[[#This Row],[Order Date]]),MONTH(Orders[[#This Row],[Order Date]]),1) -> 46023 | W44: =IF(Orders[[#This Row],[Order Status]]="Cancelled",Orders[[#This Row],[Net Sales]],0) -> 0
A45: ORD-10044 | B45: 46259 | C45: CUST-1195 | D45: Customer 1143 | E45: South | F45: Bengaluru | G45: Moisturizer | H45: Beauty | I45: 1 | J45: 599 | K45: 0.1 | L45: Net Banking | M45: Delivered | N45: 46262 | O45: 46261 | P45: =Orders[[#This Row],[Quantity]]*Orders[[#This Row],[Unit Price]] -> 599 | Q45: =Orders[[#This Row],[Gross Sales]]*Orders[[#This Row],[Discount %]] -> 59.9 | R45: =Orders[[#This Row],[Gross Sales]]-Orders[[#This Row],[Discount Amount]] -> 539.1 | S45: =IF(Orders[[#This Row],[Actual Delivery Date]]="","",Orders[[#This Row],[Actual Delivery Date]]-Orders[[#This Row],[Order Date]]) -> 2 | T45: =IF(Orders[[#This Row],[Actual Delivery Date]]="","Pending",IF(Orders[[#This Row],[Actual Delivery Date]]<=Orders[[#This Row],[Expected Delivery Date]],"On Time","Late")) -> On Time | U45: =TEXT(Orders[[#This Row],[Order Date]],"mmm") -> Aug | V45: =DATE(YEAR(Orders[[#This Row],[Order Date]]),MONTH(Orders[[#This Row],[Order Date]]),1) -> 46235 | W45: =IF(Orders[[#This Row],[Order Status]]="Cancelled",Orders[[#This Row],[Net Sales]],0) -> 0
A46: ORD-10045 | B46: 46032 | C46: CUST-1021 | D46: Customer 1016 | E46: East | F46: Patna | G46: Power Bank | H46: Electronics | I46: 2 | J46: 1499 | K46: 0 | L46: Debit Card | M46: Delivered | N46: 46039 | O46: 46038 | P46: =Orders[[#This Row],[Quantity]]*Orders[[#This Row],[Unit Price]] -> 2998 | Q46: =Orders[[#This Row],[Gross Sales]]*Orders[[#This Row],[Discount %]] -> 0 | R46: =Orders[[#This Row],[Gross Sales]]-Orders[[#This Row],[Discount Amount]] -> 2998 | S46: =IF(Orders[[#This Row],[Actual Delivery Date]]="","",Orders[[#This Row],[Actual Delivery Date]]-Orders[[#This Row],[Order Date]]) -> 6 | T46: =IF(Orders[[#This Row],[Actual Delivery Date]]="","Pending",IF(Orders[[#This Row],[Actual Delivery Date]]<=Orders[[#This Row],[Expected Delivery Date]],"On Time","Late")) -> On Time | U46: =TEXT(Orders[[#This Row],[Order Date]],"mmm") -> Jan | V46: =DATE(YEAR(Orders[[#This Row],[Order Date]]),MONTH(Orders[[#This Row],[Order Date]]),1) -> 46023 | W46: =IF(Orders[[#This Row],[Order Status]]="Cancelled",Orders[[#This Row],[Net Sales]],0) -> 0
A47: ORD-10046 | B47: 46101 | C47: CUST-1239 | D47: Customer 1132 | E47: West | F47: Pune | G47: USB-C Hub | H47: Electronics | I47: 1 | J47: 1799 | K47: 0.15 | L47: UPI | M47: Pending | N47: 46104 | P47: =Orders[[#This Row],[Quantity]]*Orders[[#This Row],[Unit Price]] -> 1799 | Q47: =Orders[[#This Row],[Gross Sales]]*Orders[[#This Row],[Discount %]] -> 269.85 | R47: =Orders[[#This Row],[Gross Sales]]-Orders[[#This Row],[Discount Amount]] -> 1529.15 | S47: =IF(Orders[[#This Row],[Actual Delivery Date]]="","",Orders[[#This Row],[Actual Delivery Date]]-Orders[[#This Row],[Order Date]]) | T47: =IF(Orders[[#This Row],[Actual Delivery Date]]="","Pending",IF(Orders[[#This Row],[Actual Delivery Date]]<=Orders[[#This Row],[Expected Delivery Date]],"On Time","Late")) -> Pending | U47: =TEXT(Orders[[#This Row],[Order Date]],"mmm") -> Mar | V47: =DATE(YEAR(Orders[[#This Row],[Order Date]]),MONTH(Orders[[#This Row],[Order Date]]),1) -> 46082 | W47: =IF(Orders[[#This Row],[Order Status]]="Cancelled",Orders[[#This Row],[Net Sales]],0) -> 0
A48: ORD-10047 | B48: 46081 | C48: CUST-1295 | D48: Customer 1193 | E48: North | F48: Jaipur | G48: Football | H48: Sports | I48: 3 | J48: 1199 | K48: 0.05 | L48: Debit Card | M48: Delivered | N48: 46087 | O48: 46084 | P48: =Orders[[#This Row],[Quantity]]*Orders[[#This Row],[Unit Price]] -> 3597 | Q48: =Orders[[#This Row],[Gross Sales]]*Orders[[#This Row],[Discount %]] -> 179.85 | R48: =Orders[[#This Row],[Gross Sales]]-Orders[[#This Row],[Discount Amount]] -> 3417.15 | S48: =IF(Orders[[#This Row],[Actual Delivery Date]]="","",Orders[[#This Row],[Actual Delivery Date]]-Orders[[#This Row],[Order Date]]) -> 3 | T48: =IF(Orders[[#This Row],[Actual Delivery Date]]="","Pending",IF(Orders[[#This Row],[Actual Delivery Date]]<=Orders[[#This Row],[Expected Delivery Date]],"On Time","Late")) -> On Time | U48: =TEXT(Orders[[#This Row],[Order Date]],"mmm") -> Feb | V48: =DATE(YEAR(Orders[[#This Row],[Order Date]]),MONTH(Orders[[#This Row],[Order Date]]),1) -> 46054 | W48: =IF(Orders[[#This Row],[Order Status]]="Cancelled",Orders[[#This Row],[Net Sales]],0) -> 0
A49: ORD-10048 | B49: 46376 | C49: CUST-1290 | D49: Customer 1022 | E49: East | F49: Bhubaneswar | G49: USB-C Hub | H49: Electronics | I49: 3 | J49: 1799 | K49: 0.05 | L49: UPI | M49: Cancelled | N49: 46380 | O49: 46377 | P49: =Orders[[#This Row],[Quantity]]*Orders[[#This Row],[Unit Price]] -> 5397 | Q49: =Orders[[#This Row],[Gross Sales]]*Orders[[#This Row],[Discount %]] -> 269.85 | R49: =Orders[[#This Row],[Gross Sales]]-Orders[[#This Row],[Discount Amount]] -> 5127.15 | S49: =IF(Orders[[#This Row],[Actual Delivery Date]]="","",Orders[[#This Row],[Actual Delivery Date]]-Orders[[#This Row],[Order Date]]) -> 1 | T49: =IF(Orders[[#This Row],[Actual Delivery Date]]="","Pending",IF(Orders[[#This Row],[Actual Delivery Date]]<=Orders[[#This Row],[Expected Delivery Date]],"On Time","Late")) -> On Time | U49: =TEXT(Orders[[#This Row],[Order Date]],"mmm") -> Dec | V49: =DATE(YEAR(Orders[[#This Row],[Order Date]]),MONTH(Orders[[#This Row],[Order Date]]),1) -> 46357 | W49: =IF(Orders[[#This Row],[Order Status]]="Cancelled",Orders[[#This Row],[Net Sales]],0) -> 5127.15
A50: ORD-10049 | B50: 46282 | C50: CUST-1236 | D50: Customer 1079 | E50: North | F50: Chandigarh | G50: T-Shirt | H50: Fashion | I50: 2 | J50: 699 | K50: 0 | L50: Net Banking | M50: Returned | N50: 46287 | O50: 46285 | P50: =Orders[[#This Row],[Quantity]]*Orders[[#This Row],[Unit Price]] -> 1398 | Q50: =Orders[[#This Row],[Gross Sales]]*Orders[[#This Row],[Discount %]] -> 0 | R50: =Orders[[#This Row],[Gross Sales]]-Orders[[#This Row],[Discount Amount]] -> 1398 | S50: =IF(Orders[[#This Row],[Actual Delivery Date]]="","",Orders[[#This Row],[Actual Delivery Date]]-Orders[[#This Row],[Order Date]]) -> 3 | T50: =IF(Orders[[#This Row],[Actual Delivery Date]]="","Pending",IF(Orders[[#This Row],[Actual Delivery Date]]<=Orders[[#This Row],[Expected Delivery Date]],"On Time","Late")) -> On Time | U50: =TEXT(Orders[[#This Row],[Order Date]],"mmm") -> Sep | V50: =DATE(YEAR(Orders[[#This Row],[Order Date]]),MONTH(Orders[[#This Row],[Order Date]]),1) -> 46266 | W50: =IF(Orders[[#This Row],[Order Status]]="Cancelled",Orders[[#This Row],[Net Sales]],0) -> 0
A51: ORD-10050 | B51: 46338 | C51: CUST-1138 | D51: Customer 1166 | E51: East | F51: Bhubaneswar | G51: Running Shoes | H51: Sports | I51: 3 | J51: 3299 | K51: 0.2 | L51: Net Banking | M51: Delivered | N51: 46343 | O51: 46343 | P51: =Orders[[#This Row],[Quantity]]*Orders[[#This Row],[Unit Price]] -> 9897 | Q51: =Orders[[#This Row],[Gross Sales]]*Orders[[#This Row],[Discount %]] -> 1979.4 | R51: =Orders[[#This Row],[Gross Sales]]-Orders[[#This Row],[Discount Amount]] -> 7917.6 | S51: =IF(Orders[[#This Row],[Actual Delivery Date]]="","",Orders[[#This Row],[Actual Delivery Date]]-Orders[[#This Row],[Order Date]]) -> 5 | T51: =IF(Orders[[#This Row],[Actual Delivery Date]]="","Pending",IF(Orders[[#This Row],[Actual Delivery Date]]<=Orders[[#This Row],[Expected Delivery Date]],"On Time","Late")) -> On Time | U51: =TEXT(Orders[[#This Row],[Order Date]],"mmm") -> Nov | V51: =DATE(YEAR(Orders[[#This Row],[Order Date]]),MONTH(Orders[[#This Row],[Order Date]]),1) -> 46327 | W51: =IF(Orders[[#This Row],[Order Status]]="Cancelled",Orders[[#This Row],[Net Sales]],0) -> 0
A52: ORD-10051 | B52: 46147 | C52: CUST-1167 | D52: Customer 1094 | E52: West | F52: Mumbai | G52: Sneakers | H52: Fashion | I52: 3 | J52: 2999 | K52: 0.2 | L52: COD | M52: Cancelled | N52: 46152 | O52: 46151 | P52: =Orders[[#This Row],[Quantity]]*Orders[[#This Row],[Unit Price]] -> 8997 | Q52: =Orders[[#This Row],[Gross Sales]]*Orders[[#This Row],[Discount %]] -> 1799.4 | R52: =Orders[[#This Row],[Gross Sales]]-Orders[[#This Row],[Discount Amount]] -> 7197.6 | S52: =IF(Orders[[#This Row],[Actual Delivery Date]]="","",Orders[[#This Row],[Actual Delivery Date]]-Orders[[#This Row],[Order Date]]) -> 4 | T52: =IF(Orders[[#This Row],[Actual Delivery Date]]="","Pending",IF(Orders[[#This Row],[Actual Delivery Date]]<=Orders[[#This Row],[Expected Delivery Date]],"On Time","Late")) -> On Time | U52: =TEXT(Orders[[#This Row],[Order Date]],"mmm") -> May | V52: =DATE(YEAR(Orders[[#This Row],[Order Date]]),MONTH(Orders[[#This Row],[Order Date]]),1) -> 46143 | W52: =IF(Orders[[#This Row],[Order Status]]="Cancelled",Orders[[#This Row],[Net Sales]],0) -> 7197.6
A53: ORD-10052 | B53: 46197 | C53: CUST-1265 | D53: Customer 1098 | E53: East | F53: Bhubaneswar | G53: Hoodie | H53: Fashion | I53: 1 | J53: 1999 | K53: 0.2 | L53: Debit Card | M53: Pending | N53: 46199 | P53: =Orders[[#This Row],[Quantity]]*Orders[[#This Row],[Unit Price]] -> 1999 | Q53: =Orders[[#This Row],[Gross Sales]]*Orders[[#This Row],[Discount %]] -> 399.8 | R53: =Orders[[#This Row],[Gross Sales]]-Orders[[#This Row],[Discount Amount]] -> 1599.2 | S53: =IF(Orders[[#This Row],[Actual Delivery Date]]="","",Orders[[#This Row],[Actual Delivery Date]]-Orders[[#This Row],[Order Date]]) | T53: =IF(Orders[[#This Row],[Actual Delivery Date]]="","Pending",IF(Orders[[#This Row],[Actual Delivery Date]]<=Orders[[#This Row],[Expected Delivery Date]],"On Time","Late")) -> Pending | U53: =TEXT(Orders[[#This Row],[Order Date]],"mmm") -> Jun | V53: =DATE(YEAR(Orders[[#This Row],[Order Date]]),MONTH(Orders[[#This Row],[Order Date]]),1) -> 46174 | W53: =IF(Orders[[#This Row],[Order Status]]="Cancelled",Orders[[#This Row],[Net Sales]],0) -> 0
A54: ORD-10053 | B54: 46307 | C54: CUST-1208 | D54: Customer 1125 | E54: South | F54: Chennai | G54: Shampoo | H54: Beauty | I54: 3 | J54: 499 | K54: 0.15 | L54: Net Banking | M54: Delivered | N54: 46309 | O54: 46308 | P54: =Orders[[#This Row],[Quantity]]*Orders[[#This Row],[Unit Price]] -> 1497 | Q54: =Orders[[#This Row],[Gross Sales]]*Orders[[#This Row],[Discount %]] -> 224.55 | R54: =Orders[[#This Row],[Gross Sales]]-Orders[[#This Row],[Discount Amount]] -> 1272.45 | S54: =IF(Orders[[#This Row],[Actual Delivery Date]]="","",Orders[[#This Row],[Actual Delivery Date]]-Orders[[#This Row],[Order Date]]) -> 1 | T54: =IF(Orders[[#This Row],[Actual Delivery Date]]="","Pending",IF(Orders[[#This Row],[Actual Delivery Date]]<=Orders[[#This Row],[Expected Delivery Date]],"On Time","Late")) -> On Time | U54: =TEXT(Orders[[#This Row],[Order Date]],"mmm") -> Oct | V54: =DATE(YEAR(Orders[[#This Row],[Order Date]]),MONTH(Orders[[#This Row],[Order Date]]),1) -> 46296 | W54: =IF(Orders[[#This Row],[Order Status]]="Cancelled",Orders[[#This Row],[Net Sales]],0) -> 0
A55: ORD-10054 | B55: 46294 | C55: CUST-1129 | D55: Customer 1119 | E55: North | F55: Lucknow | G55: Perfume | H55: Beauty | I55: 1 | J55: 1499 | K55: 0.2 | L55: Debit Card | M55: Delivered | N55: 46301 | O55: 46297 | P55: =Orders[[#This Row],[Quantity]]*Orders[[#This Row],[Unit Price]] -> 1499 | Q55: =Orders[[#This Row],[Gross Sales]]*Orders[[#This Row],[Discount %]] -> 299.8 | R55: =Orders[[#This Row],[Gross Sales]]-Orders[[#This Row],[Discount Amount]] -> 1199.2 | S55: =IF(Orders[[#This Row],[Actual Delivery Date]]="","",Orders[[#This Row],[Actual Delivery Date]]-Orders[[#This Row],[Order Date]]) -> 3 | T55: =IF(Orders[[#This Row],[Actual Delivery Date]]="","Pending",IF(Orders[[#This Row],[Actual Delivery Date]]<=Orders[[#This Row],[Expected Delivery Date]],"On Time","Late")) -> On Time | U55: =TEXT(Orders[[#This Row],[Order Date]],"mmm") -> Sep | V55: =DATE(YEAR(Orders[[#This Row],[Order Date]]),MONTH(Orders[[#This Row],[Order Date]]),1) -> 46266 | W55: =IF(Orders[[#This Row],[Order Status]]="Cancelled",Orders[[#This Row],[Net Sales]],0) -> 0
A56: ORD-10055 | B56: 46297 | C56: CUST-1269 | D56: Customer 1145 | E56: South | F56: Chennai | G56: T-Shirt | H56: Fashion | I56: 4 | J56: 699 | K56: 0.05 | L56: Credit Card | M56: Delivered | N56: 46304 | O56: 46303 | P56: =Orders[[#This Row],[Quantity]]*Orders[[#This Row],[Unit Price]] -> 2796 | Q56: =Orders[[#This Row],[Gross Sales]]*Orders[[#This Row],[Discount %]] -> 139.8 | R56: =Orders[[#This Row],[Gross Sales]]-Orders[[#This Row],[Discount Amount]] -> 2656.2 | S56: =IF(Orders[[#This Row],[Actual Delivery Date]]="","",Orders[[#This Row],[Actual Delivery Date]]-Orders[[#This Row],[Order Date]]) -> 6 | T56: =IF(Orders[[#This Row],[Actual Delivery Date]]="","Pending",IF(Orders[[#This Row],[Actual Delivery Date]]<=Orders[[#This Row],[Expected Delivery Date]],"On Time","Late")) -> On Time | U56: =TEXT(Orders[[#This Row],[Order Date]],"mmm") -> Oct | V56: =DATE(YEAR(Orders[[#This Row],[Order Date]]),MONTH(Orders[[#This Row],[Order Date]]),1) -> 46296 | W56: =IF(Orders[[#This Row],[Order Status]]="Cancelled",Orders[[#This Row],[Net Sales]],0) -> 0
A57: ORD-10056 | B57: 46207 | C57: CUST-1284 | D57: Customer 1150 | E57: South | F57: Chennai | G57: Jeans | H57: Fashion | I57: 1 | J57: 1799 | K57: 0 | L57: COD | M57: Delivered | N57: 46211 | O57: 46208 | P57: =Orders[[#This Row],[Quantity]]*Orders[[#This Row],[Unit Price]] -> 1799 | Q57: =Orders[[#This Row],[Gross Sales]]*Orders[[#This Row],[Discount %]] -> 0 | R57: =Orders[[#This Row],[Gross Sales]]-Orders[[#This Row],[Discount Amount]] -> 1799 | S57: =IF(Orders[[#This Row],[Actual Delivery Date]]="","",Orders[[#This Row],[Actual Delivery Date]]-Orders[[#This Row],[Order Date]]) -> 1 | T57: =IF(Orders[[#This Row],[Actual Delivery Date]]="","Pending",IF(Orders[[#This Row],[Actual Delivery Date]]<=Orders[[#This Row],[Expected Delivery Date]],"On Time","Late")) -> On Time | U57: =TEXT(Orders[[#This Row],[Order Date]],"mmm") -> Jul | V57: =DATE(YEAR(Orders[[#This Row],[Order Date]]),MONTH(Orders[[#This Row],[Order Date]]),1) -> 46204 | W57: =IF(Orders[[#This Row],[Order Status]]="Cancelled",Orders[[#This Row],[Net Sales]],0) -> 0
A58: ORD-10057 | B58: 46316 | C58: CUST-1245 | D58: Customer 1059 | E58: West | F58: Goa | G58: Wireless Mouse | H58: Electronics | I58: 1 | J58: 799 | K58: 0.15 | L58: Net Banking | M58: Delivered | N58: 46319 | O58: 46322 | P58: =Orders[[#This Row],[Quantity]]*Orders[[#This Row],[Unit Price]] -> 799 | Q58: =Orders[[#This Row],[Gross Sales]]*Orders[[#This Row],[Discount %]] -> 119.85 | R58: =Orders[[#This Row],[Gross Sales]]-Orders[[#This Row],[Discount Amount]] -> 679.15 | S58: =IF(Orders[[#This Row],[Actual Delivery Date]]="","",Orders[[#This Row],[Actual Delivery Date]]-Orders[[#This Row],[Order Date]]) -> 6 | T58: =IF(Orders[[#This Row],[Actual Delivery Date]]="","Pending",IF(Orders[[#This Row],[Actual Delivery Date]]<=Orders[[#This Row],[Expected Delivery Date]],"On Time","Late")) -> Late | U58: =TEXT(Orders[[#This Row],[Order Date]],"mmm") -> Oct | V58: =DATE(YEAR(Orders[[#This Row],[Order Date]]),MONTH(Orders[[#This Row],[Order Date]]),1) -> 46296 | W58: =IF(Orders[[#This Row],[Order Status]]="Cancelled",Orders[[#This Row],[Net Sales]],0) -> 0
A59: ORD-10058 | B59: 46318 | C59: CUST-1128 | D59: Customer 1061 | E59: South | F59: Kochi | G59: Face Wash | H59: Beauty | I59: 2 | J59: 399 | K59: 0 | L59: Credit Card | M59: Delivered | N59: 46324 | O59: 46325 | P59: =Orders[[#This Row],[Quantity]]*Orders[[#This Row],[Unit Price]] -> 798 | Q59: =Orders[[#This Row],[Gross Sales]]*Orders[[#This Row],[Discount %]] -> 0 | R59: =Orders[[#This Row],[Gross Sales]]-Orders[[#This Row],[Discount Amount]] -> 798 | S59: =IF(Orders[[#This Row],[Actual Delivery Date]]="","",Orders[[#This Row],[Actual Delivery Date]]-Orders[[#This Row],[Order Date]]) -> 7 | T59: =IF(Orders[[#This Row],[Actual Delivery Date]]="","Pending",IF(Orders[[#This Row],[Actual Delivery Date]]<=Orders[[#This Row],[Expected Delivery Date]],"On Time","Late")) -> Late | U59: =TEXT(Orders[[#This Row],[Order Date]],"mmm") -> Oct | V59: =DATE(YEAR(Orders[[#This Row],[Order Date]]),MONTH(Orders[[#This Row],[Order Date]]),1) -> 46296 | W59: =IF(Orders[[#This Row],[Order Status]]="Cancelled",Orders[[#This Row],[Net Sales]],0) -> 0
A60: ORD-10059 | B60: 46253 | C60: CUST-1051 | D60: Customer 1107 | E60: East | F60: Bhubaneswar | G60: Cricket Bat | H60: Sports | I60: 4 | J60: 2499 | K60: 0.1 | L60: COD | M60: Delivered | N60: 46257 | O60: 46254 | P60: =Orders[[#This Row],[Quantity]]*Orders[[#This Row],[Unit Price]] -> 9996 | Q60: =Orders[[#This Row],[Gross Sales]]*Orders[[#This Row],[Discount %]] -> 999.6 | R60: =Orders[[#This Row],[Gross Sales]]-Orders[[#This Row],[Discount Amount]] -> 8996.4 | S60: =IF(Orders[[#This Row],[Actual Delivery Date]]="","",Orders[[#This Row],[Actual Delivery Date]]-Orders[[#This Row],[Order Date]]) -> 1 | T60: =IF(Orders[[#This Row],[Actual Delivery Date]]="","Pending",IF(Orders[[#This Row],[Actual Delivery Date]]<=Orders[[#This Row],[Expected Delivery Date]],"On Time","Late")) -> On Time | U60: =TEXT(Orders[[#This Row],[Order Date]],"mmm") -> Aug | V60: =DATE(YEAR(Orders[[#This Row],[Order Date]]),MONTH(Orders[[#This Row],[Order Date]]),1) -> 46235 | W60: =IF(Orders[[#This Row],[Order Status]]="Cancelled",Orders[[#This Row],[Net Sales]],0) -> 0
A61: ORD-10060 | B61: 46145 | C61: CUST-1241 | D61: Customer 1150 | E61: West | F61: Ahmedabad | G61: Keyboard | H61: Electronics | I61: 1 | J61: 1299 | K61: 0 | L61: Credit Card | M61: Delivered | N61: 46150 | O61: 46150 | P61: =Orders[[#This Row],[Quantity]]*Orders[[#This Row],[Unit Price]] -> 1299 | Q61: =Orders[[#This Row],[Gross Sales]]*Orders[[#This Row],[Discount %]] -> 0 | R61: =Orders[[#This Row],[Gross Sales]]-Orders[[#This Row],[Discount Amount]] -> 1299 | S61: =IF(Orders[[#This Row],[Actual Delivery Date]]="","",Orders[[#This Row],[Actual Delivery Date]]-Orders[[#This Row],[Order Date]]) -> 5 | T61: =IF(Orders[[#This Row],[Actual Delivery Date]]="","Pending",IF(Orders[[#This Row],[Actual Delivery Date]]<=Orders[[#This Row],[Expected Delivery Date]],"On Time","Late")) -> On Time | U61: =TEXT(Orders[[#This Row],[Order Date]],"mmm") -> May | V61: =DATE(YEAR(Orders[[#This Row],[Order Date]]),MONTH(Orders[[#This Row],[Order Date]]),1) -> 46143 | W61: =IF(Orders[[#This Row],[Order Status]]="Cancelled",Orders[[#This Row],[Net Sales]],0) -> 0
A62: ORD-10061 | B62: 46382 | C62: CUST-1102 | D62: Customer 1218 | E62: South | F62: Chennai | G62: Hoodie | H62: Fashion | I62: 3 | J62: 1999 | K62: 0 | L62: Credit Card | M62: Delivered | N62: 46389 | O62: 46389 | P62: =Orders[[#This Row],[Quantity]]*Orders[[#This Row],[Unit Price]] -> 5997 | Q62: =Orders[[#This Row],[Gross Sales]]*Orders[[#This Row],[Discount %]] -> 0 | R62: =Orders[[#This Row],[Gross Sales]]-Orders[[#This Row],[Discount Amount]] -> 5997 | S62: =IF(Orders[[#This Row],[Actual Delivery Date]]="","",Orders[[#This Row],[Actual Delivery Date]]-Orders[[#This Row],[Order Date]]) -> 7 | T62: =IF(Orders[[#This Row],[Actual Delivery Date]]="","Pending",IF(Orders[[#This Row],[Actual Delivery Date]]<=Orders[[#This Row],[Expected Delivery Date]],"On Time","Late")) -> On Time | U62: =TEXT(Orders[[#This Row],[Order Date]],"mmm") -> Dec | V62: =DATE(YEAR(Orders[[#This Row],[Order Date]]),MONTH(Orders[[#This Row],[Order Date]]),1) -> 46357 | W62: =IF(Orders[[#This Row],[Order Status]]="Cancelled",Orders[[#This Row],[Net Sales]],0) -> 0
A63: ORD-10062 | B63: 46095 | C63: CUST-1292 | D63: Customer 1148 | E63: South | F63: Chennai | G63: Storage Box | H63: Home | I63: 1 | J63: 899 | K63: 0.05 | L63: Debit Card | M63: Pending | N63: 46102 | P63: =Orders[[#This Row],[Quantity]]*Orders[[#This Row],[Unit Price]] -> 899 | Q63: =Orders[[#This Row],[Gross Sales]]*Orders[[#This Row],[Discount %]] -> 44.95 | R63: =Orders[[#This Row],[Gross Sales]]-Orders[[#This Row],[Discount Amount]] -> 854.05 | S63: =IF(Orders[[#This Row],[Actual Delivery Date]]="","",Orders[[#This Row],[Actual Delivery Date]]-Orders[[#This Row],[Order Date]]) | T63: =IF(Orders[[#This Row],[Actual Delivery Date]]="","Pending",IF(Orders[[#This Row],[Actual Delivery Date]]<=Orders[[#This Row],[Expected Delivery Date]],"On Time","Late")) -> Pending | U63: =TEXT(Orders[[#This Row],[Order Date]],"mmm") -> Mar | V63: =DATE(YEAR(Orders[[#This Row],[Order Date]]),MONTH(Orders[[#This Row],[Order Date]]),1) -> 46082 | W63: =IF(Orders[[#This Row],[Order Status]]="Cancelled",Orders[[#This Row],[Net Sales]],0) -> 0
A64: ORD-10063 | B64: 46381 | C64: CUST-1225 | D64: Customer 1042 | E64: East | F64: Kolkata | G64: Sunscreen | H64: Beauty | I64: 1 | J64: 749 | K64: 0.1 | L64: COD | M64: Pending | N64: 46386 | P64: =Orders[[#This Row],[Quantity]]*Orders[[#This Row],[Unit Price]] -> 749 | Q64: =Orders[[#This Row],[Gross Sales]]*Orders[[#This Row],[Discount %]] -> 74.9 | R64: =Orders[[#This Row],[Gross Sales]]-Orders[[#This Row],[Discount Amount]] -> 674.1 | S64: =IF(Orders[[#This Row],[Actual Delivery Date]]="","",Orders[[#This Row],[Actual Delivery Date]]-Orders[[#This Row],[Order Date]]) | T64: =IF(Orders[[#This Row],[Actual Delivery Date]]="","Pending",IF(Orders[[#This Row],[Actual Delivery Date]]<=Orders[[#This Row],[Expected Delivery Date]],"On Time","Late")) -> Pending | U64: =TEXT(Orders[[#This Row],[Order Date]],"mmm") -> Dec | V64: =DATE(YEAR(Orders[[#This Row],[Order Date]]),MONTH(Orders[[#This Row],[Order Date]]),1) -> 46357 | W64: =IF(Orders[[#This Row],[Order Status]]="Cancelled",Orders[[#This Row],[Net Sales]],0) -> 0
A65: ORD-10064 | B65: 46151 | C65: CUST-1138 | D65: Customer 1296 | E65: South | F65: Kochi | G65: Backpack | H65: Fashion | I65: 1 | J65: 1899 | K65: 0.05 | L65: COD | M65: Pending | N65: 46153 | P65: =Orders[[#This Row],[Quantity]]*Orders[[#This Row],[Unit Price]] -> 1899 | Q65: =Orders[[#This Row],[Gross Sales]]*Orders[[#This Row],[Discount %]] -> 94.95 | R65: =Orders[[#This Row],[Gross Sales]]-Orders[[#This Row],[Discount Amount]] -> 1804.05 | S65: =IF(Orders[[#This Row],[Actual Delivery Date]]="","",Orders[[#This Row],[Actual Delivery Date]]-Orders[[#This Row],[Order Date]]) | T65: =IF(Orders[[#This Row],[Actual Delivery Date]]="","Pending",IF(Orders[[#This Row],[Actual Delivery Date]]<=Orders[[#This Row],[Expected Delivery Date]],"On Time","Late")) -> Pending | U65: =TEXT(Orders[[#This Row],[Order Date]],"mmm") -> May | V65: =DATE(YEAR(Orders[[#This Row],[Order Date]]),MONTH(Orders[[#This Row],[Order Date]]),1) -> 46143 | W65: =IF(Orders[[#This Row],[Order Status]]="Cancelled",Orders[[#This Row],[Net Sales]],0) -> 0
A66: ORD-10065 | B66: 46356 | C66: CUST-1252 | D66: Customer 1047 | E66: South | F66: Chennai | G66: Perfume | H66: Beauty | I66: 1 | J66: 1499 | K66: 0.1 | L66: Credit Card | M66: Pending | N66: 46361 | P66: =Orders[[#This Row],[Quantity]]*Orders[[#This Row],[Unit Price]] -> 1499 | Q66: =Orders[[#This Row],[Gross Sales]]*Orders[[#This Row],[Discount %]] -> 149.9 | R66: =Orders[[#This Row],[Gross Sales]]-Orders[[#This Row],[Discount Amount]] -> 1349.1 | S66: =IF(Orders[[#This Row],[Actual Delivery Date]]="","",Orders[[#This Row],[Actual Delivery Date]]-Orders[[#This Row],[Order Date]]) | T66: =IF(Orders[[#This Row],[Actual Delivery Date]]="","Pending",IF(Orders[[#This Row],[Actual Delivery Date]]<=Orders[[#This Row],[Expected Delivery Date]],"On Time","Late")) -> Pending | U66: =TEXT(Orders[[#This Row],[Order Date]],"mmm") -> Nov | V66: =DATE(YEAR(Orders[[#This Row],[Order Date]]),MONTH(Orders[[#This Row],[Order Date]]),1) -> 46327 | W66: =IF(Orders[[#This Row],[Order Status]]="Cancelled",Orders[[#This Row],[Net Sales]],0) -> 0
A67: ORD-10066 | B67: 46187 | C67: CUST-1206 | D67: Customer 1282 | E67: East | F67: Patna | G67: Sunscreen | H67: Beauty | I67: 2 | J67: 749 | K67: 0.05 | L67: Debit Card | M67: Delivered | N67: 46194 | O67: 46193 | P67: =Orders[[#This Row],[Quantity]]*Orders[[#This Row],[Unit Price]] -> 1498 | Q67: =Orders[[#This Row],[Gross Sales]]*Orders[[#This Row],[Discount %]] -> 74.9 | R67: =Orders[[#This Row],[Gross Sales]]-Orders[[#This Row],[Discount Amount]] -> 1423.1 | S67: =IF(Orders[[#This Row],[Actual Delivery Date]]="","",Orders[[#This Row],[Actual Delivery Date]]-Orders[[#This Row],[Order Date]]) -> 6 | T67: =IF(Orders[[#This Row],[Actual Delivery Date]]="","Pending",IF(Orders[[#This Row],[Actual Delivery Date]]<=Orders[[#This Row],[Expected Delivery Date]],"On Time","Late")) -> On Time | U67: =TEXT(Orders[[#This Row],[Order Date]],"mmm") -> Jun | V67: =DATE(YEAR(Orders[[#This Row],[Order Date]]),MONTH(Orders[[#This Row],[Order Date]]),1) -> 46174 | W67: =IF(Orders[[#This Row],[Order Status]]="Cancelled",Orders[[#This Row],[Net Sales]],0) -> 0
A68: ORD-10067 | B68: 46152 | C68: CUST-1212 | D68: Customer 1028 | E68: South | F68: Kochi | G68: Bluetooth Speaker | H68: Electronics | I68: 1 | J68: 1999 | K68: 0.15 | L68: COD | M68: Returned | N68: 46154 | O68: 46154 | P68: =Orders[[#This Row],[Quantity]]*Orders[[#This Row],[Unit Price]] -> 1999 | Q68: =Orders[[#This Row],[Gross Sales]]*Orders[[#This Row],[Discount %]] -> 299.85 | R68: =Orders[[#This Row],[Gross Sales]]-Orders[[#This Row],[Discount Amount]] -> 1699.15 | S68: =IF(Orders[[#This Row],[Actual Delivery Date]]="","",Orders[[#This Row],[Actual Delivery Date]]-Orders[[#This Row],[Order Date]]) -> 2 | T68: =IF(Orders[[#This Row],[Actual Delivery Date]]="","Pending",IF(Orders[[#This Row],[Actual Delivery Date]]<=Orders[[#This Row],[Expected Delivery Date]],"On Time","Late")) -> On Time | U68: =TEXT(Orders[[#This Row],[Order Date]],"mmm") -> May | V68: =DATE(YEAR(Orders[[#This Row],[Order Date]]),MONTH(Orders[[#This Row],[Order Date]]),1) -> 46143 | W68: =IF(Orders[[#This Row],[Order Status]]="Cancelled",Orders[[#This Row],[Net Sales]],0) -> 0
A69: ORD-10068 | B69: 46343 | C69: CUST-1225 | D69: Customer 1249 | E69: West | F69: Ahmedabad | G69: Cricket Bat | H69: Sports | I69: 1 | J69: 2499 | K69: 0 | L69: Credit Card | M69: Delivered | N69: 46349 | O69: 46346 | P69: =Orders[[#This Row],[Quantity]]*Orders[[#This Row],[Unit Price]] -> 2499 | Q69: =Orders[[#This Row],[Gross Sales]]*Orders[[#This Row],[Discount %]] -> 0 | R69: =Orders[[#This Row],[Gross Sales]]-Orders[[#This Row],[Discount Amount]] -> 2499 | S69: =IF(Orders[[#This Row],[Actual Delivery Date]]="","",Orders[[#This Row],[Actual Delivery Date]]-Orders[[#This Row],[Order Date]]) -> 3 | T69: =IF(Orders[[#This Row],[Actual Delivery Date]]="","Pending",IF(Orders[[#This Row],[Actual Delivery Date]]<=Orders[[#This Row],[Expected Delivery Date]],"On Time","Late")) -> On Time | U69: =TEXT(Orders[[#This Row],[Order Date]],"mmm") -> Nov | V69: =DATE(YEAR(Orders[[#This Row],[Order Date]]),MONTH(Orders[[#This Row],[Order Date]]),1) -> 46327 | W69: =IF(Orders[[#This Row],[Order Status]]="Cancelled",Orders[[#This Row],[Net Sales]],0) -> 0
A70: ORD-10069 | B70: 46386 | C70: CUST-1048 | D70: Customer 1116 | E70: South | F70: Bengaluru | G70: Resistance Bands | H70: Sports | I70: 1 | J70: 599 | K70: 0.2 | L70: UPI | M70: Pending | N70: 46391 | P70: =Orders[[#This Row],[Quantity]]*Orders[[#This Row],[Unit Price]] -> 599 | Q70: =Orders[[#This Row],[Gross Sales]]*Orders[[#This Row],[Discount %]] -> 119.8 | R70: =Orders[[#This Row],[Gross Sales]]-Orders[[#This Row],[Discount Amount]] -> 479.2 | S70: =IF(Orders[[#This Row],[Actual Delivery Date]]="","",Orders[[#This Row],[Actual Delivery Date]]-Orders[[#This Row],[Order Date]]) | T70: =IF(Orders[[#This Row],[Actual Delivery Date]]="","Pending",IF(Orders[[#This Row],[Actual Delivery Date]]<=Orders[[#This Row],[Expected Delivery Date]],"On Time","Late")) -> Pending | U70: =TEXT(Orders[[#This Row],[Order Date]],"mmm") -> Dec | V70: =DATE(YEAR(Orders[[#This Row],[Order Date]]),MONTH(Orders[[#This Row],[Order Date]]),1) -> 46357 | W70: =IF(Orders[[#This Row],[Order Status]]="Cancelled",Orders[[#This Row],[Net Sales]],0) -> 0
A71: ORD-10070 | B71: 46278 | C71: CUST-1242 | D71: Customer 1125 | E71: South | F71: Kochi | G71: Keyboard | H71: Electronics | I71: 4 | J71: 1299 | K71: 0.1 | L71: COD | M71: Cancelled | N71: 46282 | O71: 46282 | P71: =Orders[[#This Row],[Quantity]]*Orders[[#This Row],[Unit Price]] -> 5196 | Q71: =Orders[[#This Row],[Gross Sales]]*Orders[[#This Row],[Discount %]] -> 519.6 | R71: =Orders[[#This Row],[Gross Sales]]-Orders[[#This Row],[Discount Amount]] -> 4676.4 | S71: =IF(Orders[[#This Row],[Actual Delivery Date]]="","",Orders[[#This Row],[Actual Delivery Date]]-Orders[[#This Row],[Order Date]]) -> 4 | T71: =IF(Orders[[#This Row],[Actual Delivery Date]]="","Pending",IF(Orders[[#This Row],[Actual Delivery Date]]<=Orders[[#This Row],[Expected Delivery Date]],"On Time","Late")) -> On Time | U71: =TEXT(Orders[[#This Row],[Order Date]],"mmm") -> Sep | V71: =DATE(YEAR(Orders[[#This Row],[Order Date]]),MONTH(Orders[[#This Row],[Order Date]]),1) -> 46266 | W71: =IF(Orders[[#This Row],[Order Status]]="Cancelled",Orders[[#This Row],[Net Sales]],0) -> 4676.4
A72: ORD-10071 | B72: 46329 | C72: CUST-1137 | D72: Customer 1002 | E72: East | F72: Bhubaneswar | G72: Moisturizer | H72: Beauty | I72: 2 | J72: 599 | K72: 0.05 | L72: UPI | M72: Delivered | N72: 46334 | O72: 46334 | P72: =Orders[[#This Row],[Quantity]]*Orders[[#This Row],[Unit Price]] -> 1198 | Q72: =Orders[[#This Row],[Gross Sales]]*Orders[[#This Row],[Discount %]] -> 59.9 | R72: =Orders[[#This Row],[Gross Sales]]-Orders[[#This Row],[Discount Amount]] -> 1138.1 | S72: =IF(Orders[[#This Row],[Actual Delivery Date]]="","",Orders[[#This Row],[Actual Delivery Date]]-Orders[[#This Row],[Order Date]]) -> 5 | T72: =IF(Orders[[#This Row],[Actual Delivery Date]]="","Pending",IF(Orders[[#This Row],[Actual Delivery Date]]<=Orders[[#This Row],[Expected Delivery Date]],"On Time","Late")) -> On Time | U72: =TEXT(Orders[[#This Row],[Order Date]],"mmm") -> Nov | V72: =DATE(YEAR(Orders[[#This Row],[Order Date]]),MONTH(Orders[[#This Row],[Order Date]]),1) -> 46327 | W72: =IF(Orders[[#This Row],[Order Status]]="Cancelled",Orders[[#This Row],[Net Sales]],0) -> 0
A73: ORD-10072 | B73: 46360 | C73: CUST-1177 | D73: Customer 1171 | E73: North | F73: Lucknow | G73: Football | H73: Sports | I73: 2 | J73: 1199 | K73: 0.05 | L73: Net Banking | M73: Pending | N73: 46365 | P73: =Orders[[#This Row],[Quantity]]*Orders[[#This Row],[Unit Price]] -> 2398 | Q73: =Orders[[#This Row],[Gross Sales]]*Orders[[#This Row],[Discount %]] -> 119.9 | R73: =Orders[[#This Row],[Gross Sales]]-Orders[[#This Row],[Discount Amount]] -> 2278.1 | S73: =IF(Orders[[#This Row],[Actual Delivery Date]]="","",Orders[[#This Row],[Actual Delivery Date]]-Orders[[#This Row],[Order Date]]) | T73: =IF(Orders[[#This Row],[Actual Delivery Date]]="","Pending",IF(Orders[[#This Row],[Actual Delivery Date]]<=Orders[[#This Row],[Expected Delivery Date]],"On Time","Late")) -> Pending | U73: =TEXT(Orders[[#This Row],[Order Date]],"mmm") -> Dec | V73: =DATE(YEAR(Orders[[#This Row],[Order Date]]),MONTH(Orders[[#This Row],[Order Date]]),1) -> 46357 | W73: =IF(Orders[[#This Row],[Order Status]]="Cancelled",Orders[[#This Row],[Net Sales]],0) -> 0
A74: ORD-10073 | B74: 46380 | C74: CUST-1196 | D74: Customer 1198 | E74: East | F74: Guwahati | G74: Jeans | H74: Fashion | I74: 1 | J74: 1799 | K74: 0.15 | L74: Credit Card | M74: Returned | N74: 46385 | O74: 46384 | P74: =Orders[[#This Row],[Quantity]]*Orders[[#This Row],[Unit Price]] -> 1799 | Q74: =Orders[[#This Row],[Gross Sales]]*Orders[[#This Row],[Discount %]] -> 269.85 | R74: =Orders[[#This Row],[Gross Sales]]-Orders[[#This Row],[Discount Amount]] -> 1529.15 | S74: =IF(Orders[[#This Row],[Actual Delivery Date]]="","",Orders[[#This Row],[Actual Delivery Date]]-Orders[[#This Row],[Order Date]]) -> 4 | T74: =IF(Orders[[#This Row],[Actual Delivery Date]]="","Pending",IF(Orders[[#This Row],[Actual Delivery Date]]<=Orders[[#This Row],[Expected Delivery Date]],"On Time","Late")) -> On Time | U74: =TEXT(Orders[[#This Row],[Order Date]],"mmm") -> Dec | V74: =DATE(YEAR(Orders[[#This Row],[Order Date]]),MONTH(Orders[[#This Row],[Order Date]]),1) -> 46357 | W74: =IF(Orders[[#This Row],[Order Status]]="Cancelled",Orders[[#This Row],[Net Sales]],0) -> 0
A75: ORD-10074 | B75: 46280 | C75: CUST-1008 | D75: Customer 1074 | E75: West | F75: Goa | G75: Keyboard | H75: Electronics | I75: 4 | J75: 1299 | K75: 0.1 | L75: UPI | M75: Returned | N75: 46285 | O75: 46284 | P75: =Orders[[#This Row],[Quantity]]*Orders[[#This Row],[Unit Price]] -> 5196 | Q75: =Orders[[#This Row],[Gross Sales]]*Orders[[#This Row],[Discount %]] -> 519.6 | R75: =Orders[[#This Row],[Gross Sales]]-Orders[[#This Row],[Discount Amount]] -> 4676.4 | S75: =IF(Orders[[#This Row],[Actual Delivery Date]]="","",Orders[[#This Row],[Actual Delivery Date]]-Orders[[#This Row],[Order Date]]) -> 4 | T75: =IF(Orders[[#This Row],[Actual Delivery Date]]="","Pending",IF(Orders[[#This Row],[Actual Delivery Date]]<=Orders[[#This Row],[Expected Delivery Date]],"On Time","Late")) -> On Time | U75: =TEXT(Orders[[#This Row],[Order Date]],"mmm") -> Sep | V75: =DATE(YEAR(Orders[[#This Row],[Order Date]]),MONTH(Orders[[#This Row],[Order Date]]),1) -> 46266 | W75: =IF(Orders[[#This Row],[Order Status]]="Cancelled",Orders[[#This Row],[Net Sales]],0) -> 0
A76: ORD-10075 | B76: 46158 | C76: CUST-1163 | D76: Customer 1250 | E76: East | F76: Bhubaneswar | G76: Power Bank | H76: Electronics | I76: 1 | J76: 1499 | K76: 0.15 | L76: UPI | M76: Returned | N76: 46162 | O76: 46162 | P76: =Orders[[#This Row],[Quantity]]*Orders[[#This Row],[Unit Price]] -> 1499 | Q76: =Orders[[#This Row],[Gross Sales]]*Orders[[#This Row],[Discount %]] -> 224.85 | R76: =Orders[[#This Row],[Gross Sales]]-Orders[[#This Row],[Discount Amount]] -> 1274.15 | S76: =IF(Orders[[#This Row],[Actual Delivery Date]]="","",Orders[[#This Row],[Actual Delivery Date]]-Orders[[#This Row],[Order Date]]) -> 4 | T76: =IF(Orders[[#This Row],[Actual Delivery Date]]="","Pending",IF(Orders[[#This Row],[Actual Delivery Date]]<=Orders[[#This Row],[Expected Delivery Date]],"On Time","Late")) -> On Time | U76: =TEXT(Orders[[#This Row],[Order Date]],"mmm") -> May | V76: =DATE(YEAR(Orders[[#This Row],[Order Date]]),MONTH(Orders[[#This Row],[Order Date]]),1) -> 46143 | W76: =IF(Orders[[#This Row],[Order Status]]="Cancelled",Orders[[#This Row],[Net Sales]],0) -> 0
A77: ORD-10076 | B77: 46139 | C77: CUST-1228 | D77: Customer 1086 | E77: South | F77: Bengaluru | G77: Storage Box | H77: Home | I77: 2 | J77: 899 | K77: 0.15 | L77: UPI | M77: Returned | N77: 46146 | O77: 46140 | P77: =Orders[[#This Row],[Quantity]]*Orders[[#This Row],[Unit Price]] -> 1798 | Q77: =Orders[[#This Row],[Gross Sales]]*Orders[[#This Row],[Discount %]] -> 269.7 | R77: =Orders[[#This Row],[Gross Sales]]-Orders[[#This Row],[Discount Amount]] -> 1528.3 | S77: =IF(Orders[[#This Row],[Actual Delivery Date]]="","",Orders[[#This Row],[Actual Delivery Date]]-Orders[[#This Row],[Order Date]]) -> 1 | T77: =IF(Orders[[#This Row],[Actual Delivery Date]]="","Pending",IF(Orders[[#This Row],[Actual Delivery Date]]<=Orders[[#This Row],[Expected Delivery Date]],"On Time","Late")) -> On Time | U77: =TEXT(Orders[[#This Row],[Order Date]],"mmm") -> Apr | V77: =DATE(YEAR(Orders[[#This Row],[Order Date]]),MONTH(Orders[[#This Row],[Order Date]]),1) -> 46113 | W77: =IF(Orders[[#This Row],[Order Status]]="Cancelled",Orders[[#This Row],[Net Sales]],0) -> 0
A78: ORD-10077 | B78: 46051 | C78: CUST-1093 | D78: Customer 1088 | E78: North | F78: Delhi | G78: Bluetooth Speaker | H78: Electronics | I78: 1 | J78: 1999 | K78: 0.1 | L78: Net Banking | M78: Delivered | N78: 46054 | O78: 46054 | P78: =Orders[[#This Row],[Quantity]]*Orders[[#This Row],[Unit Price]] -> 1999 | Q78: =Orders[[#This Row],[Gross Sales]]*Orders[[#This Row],[Discount %]] -> 199.9 | R78: =Orders[[#This Row],[Gross Sales]]-Orders[[#This Row],[Discount Amount]] -> 1799.1 | S78: =IF(Orders[[#This Row],[Actual Delivery Date]]="","",Orders[[#This Row],[Actual Delivery Date]]-Orders[[#This Row],[Order Date]]) -> 3 | T78: =IF(Orders[[#This Row],[Actual Delivery Date]]="","Pending",IF(Orders[[#This Row],[Actual Delivery Date]]<=Orders[[#This Row],[Expected Delivery Date]],"On Time","Late")) -> On Time | U78: =TEXT(Orders[[#This Row],[Order Date]],"mmm") -> Jan | V78: =DATE(YEAR(Orders[[#This Row],[Order Date]]),MONTH(Orders[[#This Row],[Order Date]]),1) -> 46023 | W78: =IF(Orders[[#This Row],[Order Status]]="Cancelled",Orders[[#This Row],[Net Sales]],0) -> 0
A79: ORD-10078 | B79: 46340 | C79: CUST-1236 | D79: Customer 1131 | E79: West | F79: Mumbai | G79: Cricket Bat | H79: Sports | I79: 2 | J79: 2499 | K79: 0.15 | L79: COD | M79: Delivered | N79: 46343 | O79: 46342 | P79: =Orders[[#This Row],[Quantity]]*Orders[[#This Row],[Unit Price]] -> 4998 | Q79: =Orders[[#This Row],[Gross Sales]]*Orders[[#This Row],[Discount %]] -> 749.7 | R79: =Orders[[#This Row],[Gross Sales]]-Orders[[#This Row],[Discount Amount]] -> 4248.3 | S79: =IF(Orders[[#This Row],[Actual Delivery Date]]="","",Orders[[#This Row],[Actual Delivery Date]]-Orders[[#This Row],[Order Date]]) -> 2 | T79: =IF(Orders[[#This Row],[Actual Delivery Date]]="","Pending",IF(Orders[[#This Row],[Actual Delivery Date]]<=Orders[[#This Row],[Expected Delivery Date]],"On Time","Late")) -> On Time | U79: =TEXT(Orders[[#This Row],[Order Date]],"mmm") -> Nov | V79: =DATE(YEAR(Orders[[#This Row],[Order Date]]),MONTH(Orders[[#This Row],[Order Date]]),1) -> 46327 | W79: =IF(Orders[[#This Row],[Order Status]]="Cancelled",Orders[[#This Row],[Net Sales]],0) -> 0
A80: ORD-10079 | B80: 46103 | C80: CUST-1234 | D80: Customer 1155 | E80: South | F80: Kochi | G80: Backpack | H80: Fashion | I80: 1 | J80: 1899 | K80: 0.1 | L80: COD | M80: Delivered | N80: 46110 | O80: 46113 | P80: =Orders[[#This Row],[Quantity]]*Orders[[#This Row],[Unit Price]] -> 1899 | Q80: =Orders[[#This Row],[Gross Sales]]*Orders[[#This Row],[Discount %]] -> 189.9 | R80: =Orders[[#This Row],[Gross Sales]]-Orders[[#This Row],[Discount Amount]] -> 1709.1 | S80: =IF(Orders[[#This Row],[Actual Delivery Date]]="","",Orders[[#This Row],[Actual Delivery Date]]-Orders[[#This Row],[Order Date]]) -> 10 | T80: =IF(Orders[[#This Row],[Actual Delivery Date]]="","Pending",IF(Orders[[#This Row],[Actual Delivery Date]]<=Orders[[#This Row],[Expected Delivery Date]],"On Time","Late")) -> Late | U80: =TEXT(Orders[[#This Row],[Order Date]],"mmm") -> Mar | V80: =DATE(YEAR(Orders[[#This Row],[Order Date]]),MONTH(Orders[[#This Row],[Order Date]]),1) -> 46082 | W80: =IF(Orders[[#This Row],[Order Status]]="Cancelled",Orders[[#This Row],[Net Sales]],0) -> 0
A81: ORD-10080 | B81: 46144 | C81: CUST-1203 | D81: Customer 1141 | E81: West | F81: Goa | G81: Face Wash | H81: Beauty | I81: 1 | J81: 399 | K81: 0.1 | L81: COD | M81: Delivered | N81: 46151 | O81: 46151 | P81: =Orders[[#This Row],[Quantity]]*Orders[[#This Row],[Unit Price]] -> 399 | Q81: =Orders[[#This Row],[Gross Sales]]*Orders[[#This Row],[Discount %]] -> 39.9 | R81: =Orders[[#This Row],[Gross Sales]]-Orders[[#This Row],[Discount Amount]] -> 359.1 | S81: =IF(Orders[[#This Row],[Actual Delivery Date]]="","",Orders[[#This Row],[Actual Delivery Date]]-Orders[[#This Row],[Order Date]]) -> 7 | T81: =IF(Orders[[#This Row],[Actual Delivery Date]]="","Pending",IF(Orders[[#This Row],[Actual Delivery Date]]<=Orders[[#This Row],[Expected Delivery Date]],"On Time","Late")) -> On Time | U81: =TEXT(Orders[[#This Row],[Order Date]],"mmm") -> May | V81: =DATE(YEAR(Orders[[#This Row],[Order Date]]),MONTH(Orders[[#This Row],[Order Date]]),1) -> 46143 | W81: =IF(Orders[[#This Row],[Order Status]]="Cancelled",Orders[[#This Row],[Net Sales]],0) -> 0
A82: ORD-10081 | B82: 46169 | C82: CUST-1129 | D82: Customer 1071 | E82: South | F82: Bengaluru | G82: Cricket Bat | H82: Sports | I82: 3 | J82: 2499 | K82: 0.05 | L82: COD | M82: Returned | N82: 46173 | O82: 46171 | P82: =Orders[[#This Row],[Quantity]]*Orders[[#This Row],[Unit Price]] -> 7497 | Q82: =Orders[[#This Row],[Gross Sales]]*Orders[[#This Row],[Discount %]] -> 374.85 | R82: =Orders[[#This Row],[Gross Sales]]-Orders[[#This Row],[Discount Amount]] -> 7122.15 | S82: =IF(Orders[[#This Row],[Actual Delivery Date]]="","",Orders[[#This Row],[Actual Delivery Date]]-Orders[[#This Row],[Order Date]]) -> 2 | T82: =IF(Orders[[#This Row],[Actual Delivery Date]]="","Pending",IF(Orders[[#This Row],[Actual Delivery Date]]<=Orders[[#This Row],[Expected Delivery Date]],"On Time","Late")) -> On Time | U82: =TEXT(Orders[[#This Row],[Order Date]],"mmm") -> May | V82: =DATE(YEAR(Orders[[#This Row],[Order Date]]),MONTH(Orders[[#This Row],[Order Date]]),1) -> 46143 | W82: =IF(Orders[[#This Row],[Order Status]]="Cancelled",Orders[[#This Row],[Net Sales]],0) -> 0
A83: ORD-10082 | B83: 46040 | C83: CUST-1103 | D83: Customer 1068 | E83: South | F83: Bengaluru | G83: Sneakers | H83: Fashion | I83: 2 | J83: 2999 | K83: 0.05 | L83: UPI | M83: Delivered | N83: 46044 | O83: 46042 | P83: =Orders[[#This Row],[Quantity]]*Orders[[#This Row],[Unit Price]] -> 5998 | Q83: =Orders[[#This Row],[Gross Sales]]*Orders[[#This Row],[Discount %]] -> 299.9 | R83: =Orders[[#This Row],[Gross Sales]]-Orders[[#This Row],[Discount Amount]] -> 5698.1 | S83: =IF(Orders[[#This Row],[Actual Delivery Date]]="","",Orders[[#This Row],[Actual Delivery Date]]-Orders[[#This Row],[Order Date]]) -> 2 | T83: =IF(Orders[[#This Row],[Actual Delivery Date]]="","Pending",IF(Orders[[#This Row],[Actual Delivery Date]]<=Orders[[#This Row],[Expected Delivery Date]],"On Time","Late")) -> On Time | U83: =TEXT(Orders[[#This Row],[Order Date]],"mmm") -> Jan | V83: =DATE(YEAR(Orders[[#This Row],[Order Date]]),MONTH(Orders[[#This Row],[Order Date]]),1) -> 46023 | W83: =IF(Orders[[#This Row],[Order Status]]="Cancelled",Orders[[#This Row],[Net Sales]],0) -> 0
A84: ORD-10083 | B84: 46269 | C84: CUST-1073 | D84: Customer 1116 | E84: North | F84: Lucknow | G84: Storage Box | H84: Home | I84: 4 | J84: 899 | K84: 0.1 | L84: Debit Card | M84: Returned | N84: 46271 | O84: 46270 | P84: =Orders[[#This Row],[Quantity]]*Orders[[#This Row],[Unit Price]] -> 3596 | Q84: =Orders[[#This Row],[Gross Sales]]*Orders[[#This Row],[Discount %]] -> 359.6 | R84: =Orders[[#This Row],[Gross Sales]]-Orders[[#This Row],[Discount Amount]] -> 3236.4 | S84: =IF(Orders[[#This Row],[Actual Delivery Date]]="","",Orders[[#This Row],[Actual Delivery Date]]-Orders[[#This Row],[Order Date]]) -> 1 | T84: =IF(Orders[[#This Row],[Actual Delivery Date]]="","Pending",IF(Orders[[#This Row],[Actual Delivery Date]]<=Orders[[#This Row],[Expected Delivery Date]],"On Time","Late")) -> On Time | U84: =TEXT(Orders[[#This Row],[Order Date]],"mmm") -> Sep | V84: =DATE(YEAR(Orders[[#This Row],[Order Date]]),MONTH(Orders[[#This Row],[Order Date]]),1) -> 46266 | W84: =IF(Orders[[#This Row],[Order Status]]="Cancelled",Orders[[#This Row],[Net Sales]],0) -> 0
A85: ORD-10084 | B85: 46030 | C85: CUST-1300 | D85: Customer 1196 | E85: East | F85: Patna | G85: Power Bank | H85: Electronics | I85: 1 | J85: 1499 | K85: 0 | L85: Net Banking | M85: Delivered | N85: 46037 | O85: 46033 | P85: =Orders[[#This Row],[Quantity]]*Orders[[#This Row],[Unit Price]] -> 1499 | Q85: =Orders[[#This Row],[Gross Sales]]*Orders[[#This Row],[Discount %]] -> 0 | R85: =Orders[[#This Row],[Gross Sales]]-Orders[[#This Row],[Discount Amount]] -> 1499 | S85: =IF(Orders[[#This Row],[Actual Delivery Date]]="","",Orders[[#This Row],[Actual Delivery Date]]-Orders[[#This Row],[Order Date]]) -> 3 | T85: =IF(Orders[[#This Row],[Actual Delivery Date]]="","Pending",IF(Orders[[#This Row],[Actual Delivery Date]]<=Orders[[#This Row],[Expected Delivery Date]],"On Time","Late")) -> On Time | U85: =TEXT(Orders[[#This Row],[Order Date]],"mmm") -> Jan | V85: =DATE(YEAR(Orders[[#This Row],[Order Date]]),MONTH(Orders[[#This Row],[Order Date]]),1) -> 46023 | W85: =IF(Orders[[#This Row],[Order Status]]="Cancelled",Orders[[#This Row],[Net Sales]],0) -> 0
A86: ORD-10085 | B86: 46035 | C86: CUST-1033 | D86: Customer 1238 | E86: North | F86: Delhi | G86: Bedsheet Set | H86: Home | I86: 2 | J86: 1599 | K86: 0.2 | L86: Debit Card | M86: Pending | N86: 46038 | P86: =Orders[[#This Row],[Quantity]]*Orders[[#This Row],[Unit Price]] -> 3198 | Q86: =Orders[[#This Row],[Gross Sales]]*Orders[[#This Row],[Discount %]] -> 639.6 | R86: =Orders[[#This Row],[Gross Sales]]-Orders[[#This Row],[Discount Amount]] -> 2558.4 | S86: =IF(Orders[[#This Row],[Actual Delivery Date]]="","",Orders[[#This Row],[Actual Delivery Date]]-Orders[[#This Row],[Order Date]]) | T86: =IF(Orders[[#This Row],[Actual Delivery Date]]="","Pending",IF(Orders[[#This Row],[Actual Delivery Date]]<=Orders[[#This Row],[Expected Delivery Date]],"On Time","Late")) -> Pending | U86: =TEXT(Orders[[#This Row],[Order Date]],"mmm") -> Jan | V86: =DATE(YEAR(Orders[[#This Row],[Order Date]]),MONTH(Orders[[#This Row],[Order Date]]),1) -> 46023 | W86: =IF(Orders[[#This Row],[Order Status]]="Cancelled",Orders[[#This Row],[Net Sales]],0) -> 0
A87: ORD-10086 | B87: 46046 | C87: CUST-1199 | D87: Customer 1233 | E87: North | F87: Chandigarh | G87: Keyboard | H87: Electronics | I87: 4 | J87: 1299 | K87: 0.1 | L87: Net Banking | M87: Delivered | N87: 46048 | O87: 46047 | P87: =Orders[[#This Row],[Quantity]]*Orders[[#This Row],[Unit Price]] -> 5196 | Q87: =Orders[[#This Row],[Gross Sales]]*Orders[[#This Row],[Discount %]] -> 519.6 | R87: =Orders[[#This Row],[Gross Sales]]-Orders[[#This Row],[Discount Amount]] -> 4676.4 | S87: =IF(Orders[[#This Row],[Actual Delivery Date]]="","",Orders[[#This Row],[Actual Delivery Date]]-Orders[[#This Row],[Order Date]]) -> 1 | T87: =IF(Orders[[#This Row],[Actual Delivery Date]]="","Pending",IF(Orders[[#This Row],[Actual Delivery Date]]<=Orders[[#This Row],[Expected Delivery Date]],"On Time","Late")) -> On Time | U87: =TEXT(Orders[[#This Row],[Order Date]],"mmm") -> Jan | V87: =DATE(YEAR(Orders[[#This Row],[Order Date]]),MONTH(Orders[[#This Row],[Order Date]]),1) -> 46023 | W87: =IF(Orders[[#This Row],[Order Status]]="Cancelled",Orders[[#This Row],[Net Sales]],0) -> 0
A88: ORD-10087 | B88: 46235 | C88: CUST-1112 | D88: Customer 1228 | E88: North | F88: Chandigarh | G88: Resistance Bands | H88: Sports | I88: 2 | J88: 599 | K88: 0.15 | L88: COD | M88: Delivered | N88: 46239 | O88: 46238 | P88: =Orders[[#This Row],[Quantity]]*Orders[[#This Row],[Unit Price]] -> 1198 | Q88: =Orders[[#This Row],[Gross Sales]]*Orders[[#This Row],[Discount %]] -> 179.7 | R88: =Orders[[#This Row],[Gross Sales]]-Orders[[#This Row],[Discount Amount]] -> 1018.3 | S88: =IF(Orders[[#This Row],[Actual Delivery Date]]="","",Orders[[#This Row],[Actual Delivery Date]]-Orders[[#This Row],[Order Date]]) -> 3 | T88: =IF(Orders[[#This Row],[Actual Delivery Date]]="","Pending",IF(Orders[[#This Row],[Actual Delivery Date]]<=Orders[[#This Row],[Expected Delivery Date]],"On Time","Late")) -> On Time | U88: =TEXT(Orders[[#This Row],[Order Date]],"mmm") -> Aug | V88: =DATE(YEAR(Orders[[#This Row],[Order Date]]),MONTH(Orders[[#This Row],[Order Date]]),1) -> 46235 | W88: =IF(Orders[[#This Row],[Order Status]]="Cancelled",Orders[[#This Row],[Net Sales]],0) -> 0
A89: ORD-10088 | B89: 46374 | C89: CUST-1233 | D89: Customer 1047 | E89: East | F89: Bhubaneswar | G89: T-Shirt | H89: Fashion | I89: 1 | J89: 699 | K89: 0.1 | L89: UPI | M89: Delivered | N89: 46378 | O89: 46375 | P89: =Orders[[#This Row],[Quantity]]*Orders[[#This Row],[Unit Price]] -> 699 | Q89: =Orders[[#This Row],[Gross Sales]]*Orders[[#This Row],[Discount %]] -> 69.9 | R89: =Orders[[#This Row],[Gross Sales]]-Orders[[#This Row],[Discount Amount]] -> 629.1 | S89: =IF(Orders[[#This Row],[Actual Delivery Date]]="","",Orders[[#This Row],[Actual Delivery Date]]-Orders[[#This Row],[Order Date]]) -> 1 | T89: =IF(Orders[[#This Row],[Actual Delivery Date]]="","Pending",IF(Orders[[#This Row],[Actual Delivery Date]]<=Orders[[#This Row],[Expected Delivery Date]],"On Time","Late")) -> On Time | U89: =TEXT(Orders[[#This Row],[Order Date]],"mmm") -> Dec | V89: =DATE(YEAR(Orders[[#This Row],[Order Date]]),MONTH(Orders[[#This Row],[Order Date]]),1) -> 46357 | W89: =IF(Orders[[#This Row],[Order Status]]="Cancelled",Orders[[#This Row],[Net Sales]],0) -> 0
A90: ORD-10089 | B90: 46147 | C90: CUST-1120 | D90: Customer 1169 | E90: West | F90: Mumbai | G90: Bluetooth Speaker | H90: Electronics | I90: 5 | J90: 1999 | K90: 0.2 | L90: Credit Card | M90: Delivered | N90: 46153 | O90: 46149 | P90: =Orders[[#This Row],[Quantity]]*Orders[[#This Row],[Unit Price]] -> 9995 | Q90: =Orders[[#This Row],[Gross Sales]]*Orders[[#This Row],[Discount %]] -> 1999 | R90: =Orders[[#This Row],[Gross Sales]]-Orders[[#This Row],[Discount Amount]] -> 7996 | S90: =IF(Orders[[#This Row],[Actual Delivery Date]]="","",Orders[[#This Row],[Actual Delivery Date]]-Orders[[#This Row],[Order Date]]) -> 2 | T90: =IF(Orders[[#This Row],[Actual Delivery Date]]="","Pending",IF(Orders[[#This Row],[Actual Delivery Date]]<=Orders[[#This Row],[Expected Delivery Date]],"On Time","Late")) -> On Time | U90: =TEXT(Orders[[#This Row],[Order Date]],"mmm") -> May | V90: =DATE(YEAR(Orders[[#This Row],[Order Date]]),MONTH(Orders[[#This Row],[Order Date]]),1) -> 46143 | W90: =IF(Orders[[#This Row],[Order Status]]="Cancelled",Orders[[#This Row],[Net Sales]],0) -> 0
A91: ORD-10090 | B91: 46089 | C91: CUST-1122 | D91: Customer 1166 | E91: West | F91: Mumbai | G91: Jeans | H91: Fashion | I91: 2 | J91: 1799 | K91: 0.05 | L91: UPI | M91: Cancelled | N91: 46091 | O91: 46091 | P91: =Orders[[#This Row],[Quantity]]*Orders[[#This Row],[Unit Price]] -> 3598 | Q91: =Orders[[#This Row],[Gross Sales]]*Orders[[#This Row],[Discount %]] -> 179.9 | R91: =Orders[[#This Row],[Gross Sales]]-Orders[[#This Row],[Discount Amount]] -> 3418.1 | S91: =IF(Orders[[#This Row],[Actual Delivery Date]]="","",Orders[[#This Row],[Actual Delivery Date]]-Orders[[#This Row],[Order Date]]) -> 2 | T91: =IF(Orders[[#This Row],[Actual Delivery Date]]="","Pending",IF(Orders[[#This Row],[Actual Delivery Date]]<=Orders[[#This Row],[Expected Delivery Date]],"On Time","Late")) -> On Time | U91: =TEXT(Orders[[#This Row],[Order Date]],"mmm") -> Mar | V91: =DATE(YEAR(Orders[[#This Row],[Order Date]]),MONTH(Orders[[#This Row],[Order Date]]),1) -> 46082 | W91: =IF(Orders[[#This Row],[Order Status]]="Cancelled",Orders[[#This Row],[Net Sales]],0) -> 3418.1
A92: ORD-10091 | B92: 46087 | C92: CUST-1263 | D92: Customer 1056 | E92: South | F92: Chennai | G92: T-Shirt | H92: Fashion | I92: 2 | J92: 699 | K92: 0.2 | L92: UPI | M92: Cancelled | N92: 46089 | O92: 46089 | P92: =Orders[[#This Row],[Quantity]]*Orders[[#This Row],[Unit Price]] -> 1398 | Q92: =Orders[[#This Row],[Gross Sales]]*Orders[[#This Row],[Discount %]] -> 279.6 | R92: =Orders[[#This Row],[Gross Sales]]-Orders[[#This Row],[Discount Amount]] -> 1118.4 | S92: =IF(Orders[[#This Row],[Actual Delivery Date]]="","",Orders[[#This Row],[Actual Delivery Date]]-Orders[[#This Row],[Order Date]]) -> 2 | T92: =IF(Orders[[#This Row],[Actual Delivery Date]]="","Pending",IF(Orders[[#This Row],[Actual Delivery Date]]<=Orders[[#This Row],[Expected Delivery Date]],"On Time","Late")) -> On Time | U92: =TEXT(Orders[[#This Row],[Order Date]],"mmm") -> Mar | V92: =DATE(YEAR(Orders[[#This Row],[Order Date]]),MONTH(Orders[[#This Row],[Order Date]]),1) -> 46082 | W92: =IF(Orders[[#This Row],[Order Status]]="Cancelled",Orders[[#This Row],[Net Sales]],0) -> 1118.4
A93: ORD-10092 | B93: 46360 | C93: CUST-1056 | D93: Customer 1252 | E93: East | F93: Bhubaneswar | G93: Yoga Mat | H93: Sports | I93: 2 | J93: 899 | K93: 0.15 | L93: UPI | M93: Delivered | N93: 46365 | O93: 46364 | P93: =Orders[[#This Row],[Quantity]]*Orders[[#This Row],[Unit Price]] -> 1798 | Q93: =Orders[[#This Row],[Gross Sales]]*Orders[[#This Row],[Discount %]] -> 269.7 | R93: =Orders[[#This Row],[Gross Sales]]-Orders[[#This Row],[Discount Amount]] -> 1528.3 | S93: =IF(Orders[[#This Row],[Actual Delivery Date]]="","",Orders[[#This Row],[Actual Delivery Date]]-Orders[[#This Row],[Order Date]]) -> 4 | T93: =IF(Orders[[#This Row],[Actual Delivery Date]]="","Pending",IF(Orders[[#This Row],[Actual Delivery Date]]<=Orders[[#This Row],[Expected Delivery Date]],"On Time","Late")) -> On Time | U93: =TEXT(Orders[[#This Row],[Order Date]],"mmm") -> Dec | V93: =DATE(YEAR(Orders[[#This Row],[Order Date]]),MONTH(Orders[[#This Row],[Order Date]]),1) -> 46357 | W93: =IF(Orders[[#This Row],[Order Status]]="Cancelled",Orders[[#This Row],[Net Sales]],0) -> 0
A94: ORD-10093 | B94: 46334 | C94: CUST-1300 | D94: Customer 1281 | E94: East | F94: Kolkata | G94: Bluetooth Speaker | H94: Electronics | I94: 1 | J94: 1999 | K94: 0.05 | L94: Debit Card | M94: Pending | N94: 46341 | P94: =Orders[[#This Row],[Quantity]]*Orders[[#This Row],[Unit Price]] -> 1999 | Q94: =Orders[[#This Row],[Gross Sales]]*Orders[[#This Row],[Discount %]] -> 99.95 | R94: =Orders[[#This Row],[Gross Sales]]-Orders[[#This Row],[Discount Amount]] -> 1899.05 | S94: =IF(Orders[[#This Row],[Actual Delivery Date]]="","",Orders[[#This Row],[Actual Delivery Date]]-Orders[[#This Row],[Order Date]]) | T94: =IF(Orders[[#This Row],[Actual Delivery Date]]="","Pending",IF(Orders[[#This Row],[Actual Delivery Date]]<=Orders[[#This Row],[Expected Delivery Date]],"On Time","Late")) -> Pending | U94: =TEXT(Orders[[#This Row],[Order Date]],"mmm") -> Nov | V94: =DATE(YEAR(Orders[[#This Row],[Order Date]]),MONTH(Orders[[#This Row],[Order Date]]),1) -> 46327 | W94: =IF(Orders[[#This Row],[Order Status]]="Cancelled",Orders[[#This Row],[Net Sales]],0) -> 0
A95: ORD-10094 | B95: 46173 | C95: CUST-1283 | D95: Customer 1111 | E95: North | F95: Chandigarh | G95: Football | H95: Sports | I95: 2 | J95: 1199 | K95: 0.2 | L95: Net Banking | M95: Delivered | N95: 46180 | O95: 46179 | P95: =Orders[[#This Row],[Quantity]]*Orders[[#This Row],[Unit Price]] -> 2398 | Q95: =Orders[[#This Row],[Gross Sales]]*Orders[[#This Row],[Discount %]] -> 479.6 | R95: =Orders[[#This Row],[Gross Sales]]-Orders[[#This Row],[Discount Amount]] -> 1918.4 | S95: =IF(Orders[[#This Row],[Actual Delivery Date]]="","",Orders[[#This Row],[Actual Delivery Date]]-Orders[[#This Row],[Order Date]]) -> 6 | T95: =IF(Orders[[#This Row],[Actual Delivery Date]]="","Pending",IF(Orders[[#This Row],[Actual Delivery Date]]<=Orders[[#This Row],[Expected Delivery Date]],"On Time","Late")) -> On Time | U95: =TEXT(Orders[[#This Row],[Order Date]],"mmm") -> May | V95: =DATE(YEAR(Orders[[#This Row],[Order Date]]),MONTH(Orders[[#This Row],[Order Date]]),1) -> 46143 | W95: =IF(Orders[[#This Row],[Order Status]]="Cancelled",Orders[[#This Row],[Net Sales]],0) -> 0
A96: ORD-10095 | B96: 46196 | C96: CUST-1131 | D96: Customer 1192 | E96: East | F96: Guwahati | G96: Bedsheet Set | H96: Home | I96: 3 | J96: 1599 | K96: 0.15 | L96: Net Banking | M96: Cancelled | N96: 46198 | O96: 46198 | P96: =Orders[[#This Row],[Quantity]]*Orders[[#This Row],[Unit Price]] -> 4797 | Q96: =Orders[[#This Row],[Gross Sales]]*Orders[[#This Row],[Discount %]] -> 719.55 | R96: =Orders[[#This Row],[Gross Sales]]-Orders[[#This Row],[Discount Amount]] -> 4077.45 | S96: =IF(Orders[[#This Row],[Actual Delivery Date]]="","",Orders[[#This Row],[Actual Delivery Date]]-Orders[[#This Row],[Order Date]]) -> 2 | T96: =IF(Orders[[#This Row],[Actual Delivery Date]]="","Pending",IF(Orders[[#This Row],[Actual Delivery Date]]<=Orders[[#This Row],[Expected Delivery Date]],"On Time","Late")) -> On Time | U96: =TEXT(Orders[[#This Row],[Order Date]],"mmm") -> Jun | V96: =DATE(YEAR(Orders[[#This Row],[Order Date]]),MONTH(Orders[[#This Row],[Order Date]]),1) -> 46174 | W96: =IF(Orders[[#This Row],[Order Status]]="Cancelled",Orders[[#This Row],[Net Sales]],0) -> 4077.45
A97: ORD-10096 | B97: 46066 | C97: CUST-1288 | D97: Customer 1288 | E97: West | F97: Goa | G97: Wireless Mouse | H97: Electronics | I97: 1 | J97: 799 | K97: 0 | L97: Debit Card | M97: Returned | N97: 46069 | O97: 46069 | P97: =Orders[[#This Row],[Quantity]]*Orders[[#This Row],[Unit Price]] -> 799 | Q97: =Orders[[#This Row],[Gross Sales]]*Orders[[#This Row],[Discount %]] -> 0 | R97: =Orders[[#This Row],[Gross Sales]]-Orders[[#This Row],[Discount Amount]] -> 799 | S97: =IF(Orders[[#This Row],[Actual Delivery Date]]="","",Orders[[#This Row],[Actual Delivery Date]]-Orders[[#This Row],[Order Date]]) -> 3 | T97: =IF(Orders[[#This Row],[Actual Delivery Date]]="","Pending",IF(Orders[[#This Row],[Actual Delivery Date]]<=Orders[[#This Row],[Expected Delivery Date]],"On Time","Late")) -> On Time | U97: =TEXT(Orders[[#This Row],[Order Date]],"mmm") -> Feb | V97: =DATE(YEAR(Orders[[#This Row],[Order Date]]),MONTH(Orders[[#This Row],[Order Date]]),1) -> 46054 | W97: =IF(Orders[[#This Row],[Order Status]]="Cancelled",Orders[[#This Row],[Net Sales]],0) -> 0
A98: ORD-10097 | B98: 46363 | C98: CUST-1296 | D98: Customer 1260 | E98: North | F98: Delhi | G98: Sunscreen | H98: Beauty | I98: 4 | J98: 749 | K98: 0.15 | L98: UPI | M98: Delivered | N98: 46369 | O98: 46364 | P98: =Orders[[#This Row],[Quantity]]*Orders[[#This Row],[Unit Price]] -> 2996 | Q98: =Orders[[#This Row],[Gross Sales]]*Orders[[#This Row],[Discount %]] -> 449.4 | R98: =Orders[[#This Row],[Gross Sales]]-Orders[[#This Row],[Discount Amount]] -> 2546.6 | S98: =IF(Orders[[#This Row],[Actual Delivery Date]]="","",Orders[[#This Row],[Actual Delivery Date]]-Orders[[#This Row],[Order Date]]) -> 1 | T98: =IF(Orders[[#This Row],[Actual Delivery Date]]="","Pending",IF(Orders[[#This Row],[Actual Delivery Date]]<=Orders[[#This Row],[Expected Delivery Date]],"On Time","Late")) -> On Time | U98: =TEXT(Orders[[#This Row],[Order Date]],"mmm") -> Dec | V98: =DATE(YEAR(Orders[[#This Row],[Order Date]]),MONTH(Orders[[#This Row],[Order Date]]),1) -> 46357 | W98: =IF(Orders[[#This Row],[Order Status]]="Cancelled",Orders[[#This Row],[Net Sales]],0) -> 0
A99: ORD-10098 | B99: 46078 | C99: CUST-1288 | D99: Customer 1286 | E99: West | F99: Pune | G99: Moisturizer | H99: Beauty | I99: 1 | J99: 599 | K99: 0.2 | L99: Debit Card | M99: Delivered | N99: 46082 | O99: 46082 | P99: =Orders[[#This Row],[Quantity]]*Orders[[#This Row],[Unit Price]] -> 599 | Q99: =Orders[[#This Row],[Gross Sales]]*Orders[[#This Row],[Discount %]] -> 119.8 | R99: =Orders[[#This Row],[Gross Sales]]-Orders[[#This Row],[Discount Amount]] -> 479.2 | S99: =IF(Orders[[#This Row],[Actual Delivery Date]]="","",Orders[[#This Row],[Actual Delivery Date]]-Orders[[#This Row],[Order Date]]) -> 4 | T99: =IF(Orders[[#This Row],[Actual Delivery Date]]="","Pending",IF(Orders[[#This Row],[Actual Delivery Date]]<=Orders[[#This Row],[Expected Delivery Date]],"On Time","Late")) -> On Time | U99: =TEXT(Orders[[#This Row],[Order Date]],"mmm") -> Feb | V99: =DATE(YEAR(Orders[[#This Row],[Order Date]]),MONTH(Orders[[#This Row],[Order Date]]),1) -> 46054 | W99: =IF(Orders[[#This Row],[Order Status]]="Cancelled",Orders[[#This Row],[Net Sales]],0) -> 0
A100: ORD-10099 | B100: 46162 | C100: CUST-1290 | D100: Customer 1206 | E100: South | F100: Hyderabad | G100: Keyboard | H100: Electronics | I100: 2 | J100: 1299 | K100: 0.1 | L100: Debit Card | M100: Delivered | N100: 46164 | O100: 46163 | P100: =Orders[[#This Row],[Quantity]]*Orders[[#This Row],[Unit Price]] -> 2598 | Q100: =Orders[[#This Row],[Gross Sales]]*Orders[[#This Row],[Discount %]] -> 259.8 | R100: =Orders[[#This Row],[Gross Sales]]-Orders[[#This Row],[Discount Amount]] -> 2338.2 | S100: =IF(Orders[[#This Row],[Actual Delivery Date]]="","",Orders[[#This Row],[Actual Delivery Date]]-Orders[[#This Row],[Order Date]]) -> 1 | T100: =IF(Orders[[#This Row],[Actual Delivery Date]]="","Pending",IF(Orders[[#This Row],[Actual Delivery Date]]<=Orders[[#This Row],[Expected Delivery Date]],"On Time","Late")) -> On Time | U100: =TEXT(Orders[[#This Row],[Order Date]],"mmm") -> May | V100: =DATE(YEAR(Orders[[#This Row],[Order Date]]),MONTH(Orders[[#This Row],[Order Date]]),1) -> 46143 | W100: =IF(Orders[[#This Row],[Order Status]]="Cancelled",Orders[[#This Row],[Net Sales]],0) -> 0
A101: ORD-10100 | B101: 46294 | C101: CUST-1167 | D101: Customer 1291 | E101: South | F101: Chennai | G101: Wireless Mouse | H101: Electronics | I101: 1 | J101: 799 | K101: 0.15 | L101: Net Banking | M101: Delivered | N101: 46297 | O101: 46297 | P101: =Orders[[#This Row],[Quantity]]*Orders[[#This Row],[Unit Price]] -> 799 | Q101: =Orders[[#This Row],[Gross Sales]]*Orders[[#This Row],[Discount %]] -> 119.85 | R101: =Orders[[#This Row],[Gross Sales]]-Orders[[#This Row],[Discount Amount]] -> 679.15 | S101: =IF(Orders[[#This Row],[Actual Delivery Date]]="","",Orders[[#This Row],[Actual Delivery Date]]-Orders[[#This Row],[Order Date]]) -> 3 | T101: =IF(Orders[[#This Row],[Actual Delivery Date]]="","Pending",IF(Orders[[#This Row],[Actual Delivery Date]]<=Orders[[#This Row],[Expected Delivery Date]],"On Time","Late")) -> On Time | U101: =TEXT(Orders[[#This Row],[Order Date]],"mmm") -> Sep | V101: =DATE(YEAR(Orders[[#This Row],[Order Date]]),MONTH(Orders[[#This Row],[Order Date]]),1) -> 46266 | W101: =IF(Orders[[#This Row],[Order Status]]="Cancelled",Orders[[#This Row],[Net Sales]],0) -> 0
A102: ORD-10101 | B102: 46339 | C102: CUST-1227 | D102: Customer 1213 | E102: South | F102: Bengaluru | G102: Water Bottle | H102: Home | I102: 1 | J102: 699 | K102: 0 | L102: Debit Card | M102: Delivered | N102: 46346 | O102: 46344 | P102: =Orders[[#This Row],[Quantity]]*Orders[[#This Row],[Unit Price]] -> 699 | Q102: =Orders[[#This Row],[Gross Sales]]*Orders[[#This Row],[Discount %]] -> 0 | R102: =Orders[[#This Row],[Gross Sales]]-Orders[[#This Row],[Discount Amount]] -> 699 | S102: =IF(Orders[[#This Row],[Actual Delivery Date]]="","",Orders[[#This Row],[Actual Delivery Date]]-Orders[[#This Row],[Order Date]]) -> 5 | T102: =IF(Orders[[#This Row],[Actual Delivery Date]]="","Pending",IF(Orders[[#This Row],[Actual Delivery Date]]<=Orders[[#This Row],[Expected Delivery Date]],"On Time","Late")) -> On Time | U102: =TEXT(Orders[[#This Row],[Order Date]],"mmm") -> Nov | V102: =DATE(YEAR(Orders[[#This Row],[Order Date]]),MONTH(Orders[[#This Row],[Order Date]]),1) -> 46327 | W102: =IF(Orders[[#This Row],[Order Status]]="Cancelled",Orders[[#This Row],[Net Sales]],0) -> 0
A103: ORD-10102 | B103: 46199 | C103: CUST-1113 | D103: Customer 1203 | E103: North | F103: Jaipur | G103: Yoga Mat | H103: Sports | I103: 1 | J103: 899 | K103: 0.1 | L103: COD | M103: Delivered | N103: 46205 | O103: 46200 | P103: =Orders[[#This Row],[Quantity]]*Orders[[#This Row],[Unit Price]] -> 899 | Q103: =Orders[[#This Row],[Gross Sales]]*Orders[[#This Row],[Discount %]] -> 89.9 | R103: =Orders[[#This Row],[Gross Sales]]-Orders[[#This Row],[Discount Amount]] -> 809.1 | S103: =IF(Orders[[#This Row],[Actual Delivery Date]]="","",Orders[[#This Row],[Actual Delivery Date]]-Orders[[#This Row],[Order Date]]) -> 1 | T103: =IF(Orders[[#This Row],[Actual Delivery Date]]="","Pending",IF(Orders[[#This Row],[Actual Delivery Date]]<=Orders[[#This Row],[Expected Delivery Date]],"On Time","Late")) -> On Time | U103: =TEXT(Orders[[#This Row],[Order Date]],"mmm") -> Jun | V103: =DATE(YEAR(Orders[[#This Row],[Order Date]]),MONTH(Orders[[#This Row],[Order Date]]),1) -> 46174 | W103: =IF(Orders[[#This Row],[Order Status]]="Cancelled",Orders[[#This Row],[Net Sales]],0) -> 0
A104: ORD-10103 | B104: 46131 | C104: CUST-1090 | D104: Customer 1067 | E104: South | F104: Bengaluru | G104: Storage Box | H104: Home | I104: 3 | J104: 899 | K104: 0.1 | L104: Debit Card | M104: Delivered | N104: 46133 | O104: 46133 | P104: =Orders[[#This Row],[Quantity]]*Orders[[#This Row],[Unit Price]] -> 2697 | Q104: =Orders[[#This Row],[Gross Sales]]*Orders[[#This Row],[Discount %]] -> 269.7 | R104: =Orders[[#This Row],[Gross Sales]]-Orders[[#This Row],[Discount Amount]] -> 2427.3 | S104: =IF(Orders[[#This Row],[Actual Delivery Date]]="","",Orders[[#This Row],[Actual Delivery Date]]-Orders[[#This Row],[Order Date]]) -> 2 | T104: =IF(Orders[[#This Row],[Actual Delivery Date]]="","Pending",IF(Orders[[#This Row],[Actual Delivery Date]]<=Orders[[#This Row],[Expected Delivery Date]],"On Time","Late")) -> On Time | U104: =TEXT(Orders[[#This Row],[Order Date]],"mmm") -> Apr | V104: =DATE(YEAR(Orders[[#This Row],[Order Date]]),MONTH(Orders[[#This Row],[Order Date]]),1) -> 46113 | W104: =IF(Orders[[#This Row],[Order Status]]="Cancelled",Orders[[#This Row],[Net Sales]],0) -> 0
A105: ORD-10104 | B105: 46365 | C105: CUST-1236 | D105: Customer 1040 | E105: East | F105: Bhubaneswar | G105: Football | H105: Sports | I105: 3 | J105: 1199 | K105: 0 | L105: Net Banking | M105: Returned | N105: 46372 | O105: 46366 | P105: =Orders[[#This Row],[Quantity]]*Orders[[#This Row],[Unit Price]] -> 3597 | Q105: =Orders[[#This Row],[Gross Sales]]*Orders[[#This Row],[Discount %]] -> 0 | R105: =Orders[[#This Row],[Gross Sales]]-Orders[[#This Row],[Discount Amount]] -> 3597 | S105: =IF(Orders[[#This Row],[Actual Delivery Date]]="","",Orders[[#This Row],[Actual Delivery Date]]-Orders[[#This Row],[Order Date]]) -> 1 | T105: =IF(Orders[[#This Row],[Actual Delivery Date]]="","Pending",IF(Orders[[#This Row],[Actual Delivery Date]]<=Orders[[#This Row],[Expected Delivery Date]],"On Time","Late")) -> On Time | U105: =TEXT(Orders[[#This Row],[Order Date]],"mmm") -> Dec | V105: =DATE(YEAR(Orders[[#This Row],[Order Date]]),MONTH(Orders[[#This Row],[Order Date]]),1) -> 46357 | W105: =IF(Orders[[#This Row],[Order Status]]="Cancelled",Orders[[#This Row],[Net Sales]],0) -> 0
A106: ORD-10105 | B106: 46386 | C106: CUST-1236 | D106: Customer 1186 | E106: North | F106: Chandigarh | G106: Cricket Bat | H106: Sports | I106: 2 | J106: 2499 | K106: 0.1 | L106: UPI | M106: Delivered | N106: 46388 | O106: 46390 | P106: =Orders[[#This Row],[Quantity]]*Orders[[#This Row],[Unit Price]] -> 4998 | Q106: =Orders[[#This Row],[Gross Sales]]*Orders[[#This Row],[Discount %]] -> 499.8 | R106: =Orders[[#This Row],[Gross Sales]]-Orders[[#This Row],[Discount Amount]] -> 4498.2 | S106: =IF(Orders[[#This Row],[Actual Delivery Date]]="","",Orders[[#This Row],[Actual Delivery Date]]-Orders[[#This Row],[Order Date]]) -> 4 | T106: =IF(Orders[[#This Row],[Actual Delivery Date]]="","Pending",IF(Orders[[#This Row],[Actual Delivery Date]]<=Orders[[#This Row],[Expected Delivery Date]],"On Time","Late")) -> Late | U106: =TEXT(Orders[[#This Row],[Order Date]],"mmm") -> Dec | V106: =DATE(YEAR(Orders[[#This Row],[Order Date]]),MONTH(Orders[[#This Row],[Order Date]]),1) -> 46357 | W106: =IF(Orders[[#This Row],[Order Status]]="Cancelled",Orders[[#This Row],[Net Sales]],0) -> 0
... A114: ORD-10113 | B114: 46071 | C114: CUST-1077 | D114: Customer 1171 | E114: South | F114: Hyderabad | G114: Bluetooth Speaker | H114: Electronics | I114: 2 | J114: 1999 | K114: 0.15 | L114: Debit Card | M114: Delivered | N114: 46078 | O114: 46076 | P114: =Orders[[#This Row],[Quantity]]*Orders[[#This Row],[Unit Price]] -> 3998 | Q114: =Orders[[#This Row],[Gross Sales]]*Orders[[#This Row],[Discount %]] -> 599.7 | R114: =Orders[[#This Row],[Gross Sales]]-Orders[[#This Row],[Discount Amount]] -> 3398.3 | S114: =IF(Orders[[#This Row],[Actual Delivery Date]]="","",Orders[[#This Row],[Actual Delivery Date]]-Orders[[#This Row],[Order Date]]) -> 5 | T114: =IF(Orders[[#This Row],[Actual Delivery Date]]="","Pending",IF(Orders[[#This Row],[Actual Delivery Date]]<=Orders[[#This Row],[Expected Delivery Date]],"On Time","Late")) -> On Time | U114: =TEXT(Orders[[#This Row],[Order Date]],"mmm") -> Feb | V114: =DATE(YEAR(Orders[[#This Row],[Order Date]]),MONTH(Orders[[#This Row],[Order Date]]),1) -> 46054 | W114: =IF(Orders[[#This Row],[Order Status]]="Cancelled",Orders[[#This Row],[Net Sales]],0) -> 0
A115: ORD-10114 | B115: 46358 | C115: CUST-1044 | D115: Customer 1159 | E115: South | F115: Chennai | G115: Hoodie | H115: Fashion | I115: 2 | J115: 1999 | K115: 0.15 | L115: Credit Card | M115: Pending | N115: 46365 | P115: =Orders[[#This Row],[Quantity]]*Orders[[#This Row],[Unit Price]] -> 3998 | Q115: =Orders[[#This Row],[Gross Sales]]*Orders[[#This Row],[Discount %]] -> 599.7 | R115: =Orders[[#This Row],[Gross Sales]]-Orders[[#This Row],[Discount Amount]] -> 3398.3 | S115: =IF(Orders[[#This Row],[Actual Delivery Date]]="","",Orders[[#This Row],[Actual Delivery Date]]-Orders[[#This Row],[Order Date]]) | T115: =IF(Orders[[#This Row],[Actual Delivery Date]]="","Pending",IF(Orders[[#This Row],[Actual Delivery Date]]<=Orders[[#This Row],[Expected Delivery Date]],"On Time","Late")) -> Pending | U115: =TEXT(Orders[[#This Row],[Order Date]],"mmm") -> Dec | V115: =DATE(YEAR(Orders[[#This Row],[Order Date]]),MONTH(Orders[[#This Row],[Order Date]]),1) -> 46357 | W115: =IF(Orders[[#This Row],[Order Status]]="Cancelled",Orders[[#This Row],[Net Sales]],0) -> 0
...

Sheet Analysis
A2: Row Labels | B2: Sum of Net Sales | D2: Order Status | E2: Count of Order ID | G2: Row Labels | H2: Count of Order ID
A3: East | B3: 614373.15 | D3: Returned | E3: 133 | G3: Late | H3: 95
A4: North | B4: 630957.9 | D4: Grand Total | E4: 133 | G4: On Time | H4: 752 | J4: South Percentage | K4: =GETPIVOTDATA("Net Sales",$A$2,"Region","South")/GETPIVOTDATA("Net Sales",$A$2) -> 0.26425385
A5: South | B5: 642685.75 | G5: Pending | H5: 153 | J5: West and North | K5: =K34-K32 -> 0.015617716
A6: West | B6: 544060.35 | G6: Grand Total | H6: 1000 | J6: Sneakers | K6: =GETPIVOTDATA("Cancelled Sales",$A$121,"Product","Sneakers")/GETPIVOTDATA("Net Sales",$A$36,"Product","Sneakers") -> 0.20226415
A7: Grand Total | B7: 2432077.2 | J7: Coffee Maker % | K7: =GETPIVOTDATA("Net Sales",$A$36,"Product","Coffee Maker")/GETPIVOTDATA("Net Sales",$A$36) -> 0.10876481
G8: Completed Orders | H8: =GETPIVOTDATA("Order ID",$G$2,"Delivery Status","On Time")+GETPIVOTDATA("Order ID",$G$2,"Delivery Status","Late") -> 847 | J8: Order fulfillment | K8: =GETPIVOTDATA("Order ID",$D$2,"Order Status","Pending")/GETPIVOTDATA("Order ID",$D$2) -> #REF!
A9: Row Labels | B9: Count of Order ID | D9: Category | E9: Sum of Net Sales | G9: On-Time Orders | H9: =GETPIVOTDATA("Order ID",$G$2,"Delivery Status","On Time") -> 752
A10: East | B10: 257 | D10: Beauty | E10: 239520.05 | G10: On-Time Delivery % | H10: =GETPIVOTDATA("Order ID",$G$2,"Delivery Status","On Time")/(GETPIVOTDATA("Order ID",$G$2,"Delivery Status","On Time")+GETPIVOTDATA("Order ID",$G$2,"Delivery Status","Late")) -> 0.88783943
A11: North | B11: 260 | D11: Electronics | E11: 505171.4
A12: South | B12: 256 | D12: Fashion | E12: 583358.3 | G12: Row Labels | H12: Sum of Delivery Days
A13: West | B13: 227 | D13: Home | E13: 552275.5 | G13: Late | H13: 688
A14: Grand Total | B14: 1000 | D14: Sports | E14: 551751.9 | G14: On Time | H14: 2098
D15: Grand Total | E15: 2432077.2 | G15: Pending | H15: 0
A16: Row Labels | B16: Average of Net Sales | G16: Grand Total | H16: 2786
A17: East | B17: 2390.557 | D17: Row Labels | E17: Sum of Net Sales
A18: North | B18: 2426.7612 | D18: 46023 | E18: 209922.65 | G18: Total Delivery Days | H18: =GETPIVOTDATA("Delivery Days",$G$12,"Delivery Status","On Time")+GETPIVOTDATA("Delivery Days",$G$12,"Delivery Status","Late") -> 2786
A19: South | B19: 2510.4912 | D19: 46054 | E19: 156080.85 | G19: Average Delivery Days | H19: =H18/H8 -> 3.2892562
A20: West | B20: 2396.7416 | D20: 46082 | E20: 185487.95
A21: Grand Total | B21: 2432.0771 | D21: 46113 | E21: 240356.7 | H21: Column Labels
D22: 46143 | E22: 181337.2 | H22: Late | J22: On Time | L22: Pending | N22: Total Average of Delivery Days | O22: Total Count of Order ID
D23: 46174 | E23: 162697.2 | G23: Row Labels | H23: Average of Delivery Days | I23: Count of Order ID | J23: Average of Delivery Days | K23: Count of Order ID | L23: Average of Delivery Days | M23: Count of Order ID
D24: 46204 | E24: 231115.5 | G24: East | H24: 7.0416667 | I24: 24 | J24: 2.746114 | K24: 193 | L24: #DIV/0! | M24: 40 | N24: 3.2211982 | O24: 257
D25: 46235 | E25: 259695.65 | G25: North | H25: 7.2692308 | I25: 26 | J25: 2.7628866 | K25: 194 | L25: #DIV/0! | M25: 40 | N25: 3.2954545 | O25: 260
D26: 46266 | E26: 175760.1 | G26: South | H26: 6.96 | I26: 25 | J26: 2.7421053 | K26: 190 | L26: #DIV/0! | M26: 41 | N26: 3.2325581 | O26: 256
D27: 46296 | E27: 195569.45 | G27: West | H27: 7.8 | I27: 20 | J27: 2.92 | K27: 175 | L27: #DIV/0! | M27: 32 | N27: 3.4205128 | O27: 227
D28: 46327 | E28: 181070.4 | G28: Grand Total | H28: 7.2421053 | I28: 95 | J28: 2.7898936 | K28: 752 | L28: #DIV/0! | M28: 153 | N28: 3.2892562 | O28: 1000
D29: 46357 | E29: 252983.5
D30: Grand Total | E30: 2432077.1 | G30: Region | H30: On-Time Orders | I30: Late Orders | J30: Completed Orders | K30: On-Time Delivery %
G31: East | H31: =GETPIVOTDATA("Count of Order ID",$G$21,"Region","East","Delivery Status","On Time") -> 193 | I31: =GETPIVOTDATA("Count of Order ID",$G$21,"Region","East","Delivery Status","Late") -> 24 | J31: =H31+I31 -> 217 | K31: =H31/J31 -> 0.88940092
G32: North | H32: =GETPIVOTDATA("Count of Order ID",$G$21,"Region","North","Delivery Status","On Time") -> 194 | I32: =GETPIVOTDATA("Count of Order ID",$G$21,"Region","North","Delivery Status","Late") -> 26 | J32: =H32+I32 -> 220 | K32: =H32/J32 -> 0.88181818
G33: South | H33: =GETPIVOTDATA("Count of Order ID",$G$21,"Region","South","Delivery Status","On Time") -> 190 | I33: =GETPIVOTDATA("Count of Order ID",$G$21,"Region","South","Delivery Status","Late") -> 25 | J33: =H33+I33 -> 215 | K33: =H33/J33 -> 0.88372093
G34: West | H34: =GETPIVOTDATA("Count of Order ID",$G$21,"Region","West","Delivery Status","On Time") -> 175 | I34: =GETPIVOTDATA("Count of Order ID",$G$21,"Region","West","Delivery Status","Late") -> 20 | J34: =H34+I34 -> 195 | K34: =H34/J34 -> 0.8974359
G35: Overall On-Time Delivery % | H35: =(SUM(H31:H34))/(SUM(J31:J34)) -> 0.88783943
A36: Product | B36: Sum of Net Sales | D36: Count of Order ID | E36: Column Labels
A37: Coffee Maker | B37: 264524.4 | D37: Row Labels | E37: Cancelled | F37: Delivered | G37: Pending | H37: Returned | I37: Grand Total | J37: Cancellation Rate
A38: Running Shoes | B38: 221692.8 | D38: Backpack | E38: 3 | F38: 19 | G38: 6 | H38: 7 | I38: 35 | J38: =E38/I38 -> 0.085714286
A39: Sneakers | B39: 198683.75 | D39: Bedsheet Set | E39: 4 | F39: 21 | G39: 6 | H39: 4 | I39: 35 | J39: =E39/I39 -> 0.11428571
A40: Cricket Bat | B40: 174305.25 | D40: Bluetooth Speaker | E40: 8 | F40: 27 | G40: 9 | H40: 6 | I40: 50 | J40: =E40/I40 -> 0.16
A41: Bluetooth Speaker | B41: 160019.95 | D41: Coffee Maker | E41: 2 | F41: 29 | G41: 9 | H41: 4 | I41: 44 | J41: =E41/I41 -> 0.045454545
A42: Hoodie | B42: 125037.45 | D42: Cricket Bat | E42: 8 | F42: 25 | G42: 1 | H42: 8 | I42: 42 | J42: =E42/I42 -> 0.19047619
A43: USB-C Hub | B43: 119633.5 | D43: Desk Lamp | E43: 5 | F43: 23 | G43: 7 | H43: 5 | I43: 40 | J43: =E43/I43 -> 0.125
A44: Keyboard | B44: 106582.95 | D44: Face Wash | E44: 8 | F44: 25 | G44: 5 | H44: 3 | I44: 41 | J44: =E44/I44 -> 0.19512195
A45: Jeans | B45: 101733.45 | D45: Football | E45: 4 | F45: 17 | G45: 4 | H45: 7 | I45: 32 | J45: =E45/I45 -> 0.125
A46: Backpack | B46: 93525.75 | D46: Hoodie | E46: 7 | F46: 19 | G46: 9 | H46: 2 | I46: 37 | J46: =E46/I46 -> 0.18918919
A47: Bedsheet Set | B47: 88744.5 | D47: Jeans | E47: 6 | F47: 19 | G47: 2 | H47: 8 | I47: 35 | J47: =E47/I47 -> 0.17142857
A48: Perfume | B48: 76748.8 | D48: Keyboard | E48: 5 | F48: 29 | G48: 3 | H48: 7 | I48: 44 | J48: =E48/I48 -> 0.11363636
A49: Desk Lamp | B49: 76673.25 | D49: Moisturizer | E49: 4 | F49: 25 | G49: 4 | H49: 7 | I49: 40 | J49: =E49/I49 -> 0.1
... A58: Shampoo | B58: 44635.55 | D58: T-Shirt | E58: 8 | F58: 25 | G58: 7 | H58: 7 | I58: 47 | J58: =E58/I58 -> 0.17021277
A59: Moisturizer | B59: 35460.8 | D59: USB-C Hub | E59: 5 | F59: 19 | G59: 8 | I59: 32 | J59: =E59/I59 -> 0.15625
A60: Resistance Bands | B60: 27613.9 | D60: Water Bottle | E60: 5 | F60: 23 | G60: 4 | H60: 10 | I60: 42 | J60: =E60/I60 -> 0.11904762
A61: Face Wash | B61: 23241.75 | D61: Wireless Mouse | E61: 6 | F61: 23 | G61: 6 | H61: 8 | I61: 43 | J61: =E61/I61 -> 0.13953488
A62: Grand Total | B62: 2432077.1 | D62: Yoga Mat | E62: 4 | F62: 21 | G62: 7 | H62: 8 | I62: 40 | J62: =E62/I62 -> 0.1
D63: Grand Total | E63: 131 | F63: 583 | G63: 153 | H63: 133 | I63: 1000
A64: Row Labels | B64: Sum of Quantity
A65: Shampoo | B65: 101 | D65: Cancellation Rate | E65: =GETPIVOTDATA("Order ID",$D$36,"Order Status","Cancelled")/GETPIVOTDATA("Order ID",$D$36) -> 0.131
A66: T-Shirt | B66: 100
A67: Keyboard | B67: 94 | D67: Product | E67: Cancellation Rate | F67: Total Orders | G67: Net Sales
A68: Sunscreen | B68: 90 | D68: Resistance Bands | E68: 0.2121 | F68: 33 | G68: =GETPIVOTDATA("Net Sales",$A$36,"Product","Resistance Bands") -> 27613.9
A69: Storage Box | B69: 90 | D69: Face Wash | E69: 0.1951 | F69: 41 | G69: =GETPIVOTDATA("Net Sales",$A$36,"Product","Face Wash") -> 23241.75
A70: Bluetooth Speaker | B70: 89 | D70: Cricket Bat | E70: 0.1905 | F70: 42 | G70: =GETPIVOTDATA("Net Sales",$A$36,"Product","Cricket Bat") -> 174305.25
A71: Desk Lamp | B71: 84 | D71: Hoodie | E71: 0.1892 | F71: 37 | G71: =GETPIVOTDATA("Net Sales",$A$36,"Product","Hoodie") -> 125037.45
A72: Coffee Maker | B72: 84 | D72: T-Shirt | E72: 0.1702 | F72: 47 | G72: =GETPIVOTDATA("Net Sales",$A$36,"Product","T-Shirt") -> 64377.9
A73: Yoga Mat | B73: 79
A74: Water Bottle | B74: 77
A75: Wireless Mouse | B75: 76
A76: Sneakers | B76: 76
A77: Cricket Bat | B77: 76
A78: Running Shoes | B78: 74
A79: USB-C Hub | B79: 72
A80: Hoodie | B80: 70
A81: Moisturizer | B81: 67
A82: Face Wash | B82: 66
A83: Jeans | B83: 64
A84: Bedsheet Set | B84: 62
... A90: Grand Total | B90: 1861
A92: Row Labels | B92: Sum of Net Sales | C92: Sum of Quantity | D92: Average of Net Sales
A93: Coffee Maker | B93: 264524.4 | C93: 84 | D93: 6011.9182
A94: Running Shoes | B94: 221692.8 | C94: 74 | D94: 5991.6973
A95: Sneakers | B95: 198683.75 | C95: 76 | D95: 4515.5398
A96: Cricket Bat | B96: 174305.25 | C96: 76 | D96: 4150.125
A97: Bluetooth Speaker | B97: 160019.95 | C97: 89 | D97: 3200.399
A98: Hoodie | B98: 125037.45 | C98: 70 | D98: 3379.3905
A99: USB-C Hub | B99: 119633.5 | C99: 72 | D99: 3738.5469
A100: Keyboard | B100: 106582.95 | C100: 94 | D100: 2422.3398
A101: Jeans | B101: 101733.45 | C101: 64 | D101: 2906.67
A102: Backpack | B102: 93525.75 | C102: 53 | D102: 2672.1643
A103: Bedsheet Set | B103: 88744.5 | C103: 62 | D103: 2535.5571
A104: Perfume | B104: 76748.8 | C104: 56 | D104: 2257.3176
... A118: Grand Total | B118: 2432077.1 | C118: 1861 | D118: 2432.0771
A121: Row Labels | B121: Sum of Cancelled Sales | D121: Row Labels | E121: Sum of Net Sales | F121: Sum of Quantity | G121: Count of Order ID | H121: Sum of Cancelled Sales
A122: Sneakers | B122: 40186.6 | D122: Coffee Maker | E122: 264524.4 | F122: 84 | G122: 44 | H122: 10147.1
A123: Bluetooth Speaker | B123: 30084.95 | D123: Running Shoes | E123: 221692.8 | F123: 74 | G123: 37 | H123: 11876.4
A124: Cricket Bat | B124: 27489 | D124: Sneakers | E124: 198683.75 | F124: 76 | G124: 44 | H124: 40186.6
A125: Hoodie | B125: 25787.1 | D125: Cricket Bat | E125: 174305.25 | F125: 76 | G125: 42 | H125: 27489
A126: Jeans | B126: 24196.55 | D126: Bluetooth Speaker | E126: 160019.95 | F126: 89 | G126: 50 | H126: 30084.95
A127: USB-C Hub | B127: 18619.65 | D127: Hoodie | E127: 125037.45 | F127: 70 | G127: 37 | H127: 25787.1
A128: Keyboard | B128: 16562.25 | D128: USB-C Hub | E128: 119633.5 | F128: 72 | G128: 32 | H128: 18619.65
A129: Perfume | B129: 13865.75 | D129: Keyboard | E129: 106582.95 | F129: 94 | G129: 44 | H129: 16562.25
A130: Backpack | B130: 13293 | D130: Jeans | E130: 101733.45 | F130: 64 | G130: 35 | H130: 24196.55
...

Sheet Dashboard
A1: SALES AND OPERATIONS DATA 2026
A2: TOTAL REVENUE | C2: TOTAL ORDERS | E2: AVERAGE ORDER VALUE | G2: ON TIME DELIVERY | I2: CANCELLATION RATE | K2: AVERAGE DELIVERY DAYS
A3: =GETPIVOTDATA("Net Sales",Analysis!$A$2) -> 2432077.2 | C3: =GETPIVOTDATA("Order ID",Analysis!$A$9) -> 1000 | E3: =GETPIVOTDATA("Net Sales",Analysis!$A$16) -> 2432.0771 | G3: =Analysis!H10 -> 0.88783943 | I3: =Analysis!E65 -> 0.131 | K3: =Analysis!H19 -> 3.2892562
A82: KEY BUSINESS INSIGHTS
A84: ● South leads regional sales, contributing 26.43% of total revenue.
A86: ● Delivery performance is relatively consistent across regions;
A87: the West–North gap is only 1.56 percentage points.
A89: ● Sneakers have ₹40.2K in cancelled sales, equal to 20.23%
A90: of their net sales — a potential area for investigation.
A92: ● Coffee Maker is the top-revenue product, contributing 10.88%
A93: of total net sales.
A95: ● 15.30% of orders remain pending, indicating a significant
A96: fulfillment backlog.
